Workbook

Sheet Как читать
A1: Полная статистика публикаций канала «Валентина Хлистун | Этикет»
A3: Источник данных | B3: Дзен-студия → Статистика → Публикации → «Отчёт», период «Всё время». Выгружено 25 июля 2026 года.
A4: Что внутри | B4: 1660 публикаций: 623 статьи, 661 ролик, 369 постов, 7 видео. Даты публикации — с февраля 2023 по 24 июля 2026.
A6: Показы | B6: Сколько раз карточка публикации попала людям в ленту. Это решение алгоритма, а не заслуга текста.
A7: Открытия | B7: Сколько раз публикацию открыли. В публичной карточке канала это же число показано как «просмотры».
A8: Дочитывания | B8: Сколько человек долистали до конца.
A9: CTR = открытия / показы | B9: Первая ступень воронки. За неё отвечают обложка, заголовок и тема — то, что видно в ленте.
A10: Дочитываемость = дочитывания / открытия | B10: Вторая ступень. За неё отвечает сам текст: первый экран, длина, ритм, структура.
A11: Лайки, комментарии, подписки на дочитывание | B11: Третья ступень: реакция тех, кто действительно прочитал.
A12: Индекс к периоду | B12: Показатель статьи, делённый на медиану всех публикаций того же типа за ±90 дней. 1,00 — как обычно в те месяцы; 2,00 — вдвое лучше обычного; 0,50 — вдвое хуже. Нужен потому, что канал рос и Дзен менял алгоритм: сравнивать статью 2023 года со статьёй 2026 года напрямую нельзя.
A14: Как этим НЕ пользоваться | B14: Абсолютные просмотры и лайки не показывают качество статьи: чем больше алгоритм дал показов, тем больше будет и то и другое. Сравнивать статьи между собой можно только по долям и индексам.
A15: Разные типы — разные вселенные | B15: У роликов медианный CTR около 30%, у статей — около 5%. В одну таблицу сравнения их сводить нельзя, поэтому они на разных листах.
A16: Свежие публикации | B16: Публикации моложе 30 дней ещё не набрали хвост показов. Их показатели занижены и в сравнения не идут.
A17: Что дальше | B17: Тексты статей размечаются по справочнику критериев ОТДЕЛЬНО и ВСЛЕПУЮ — без доступа к этим цифрам. Только потом разметка соединяется со статистикой. Иначе разбор подгонит признаки под уже известный результат.

Sheet Сводка
A1: Сводка: типичные значения (медианы)
A2: Медиана, а не среднее: одна вирусная публикация искажает среднее до бессмыслицы.
A4: Группа | B4: Публикаций | C4: Показы | D4: Открытия | E4: Дочитывания | F4: CTR | G4: Дочитываемость | H4: Мин. на дочитывание | I4: Лайки/дочит. | J4: Комм./дочит. | K4: Подписки/дочит.
A5: Статьи — все | B5: =COUNT('Статьи'!$F$5:$F$627) -> 623 | C5: =IFERROR(MEDIAN('Статьи'!$F$5:$F$627),"") -> 140440 | D5: =IFERROR(MEDIAN('Статьи'!$G$5:$G$627),"") -> 10787 | E5: =IFERROR(MEDIAN('Статьи'!$H$5:$H$627),"") -> 5339 | F5: =IFERROR(MEDIAN('Статьи'!$M$5:$M$627),"") -> 0.054442563 | G5: =IFERROR(MEDIAN('Статьи'!$N$5:$N$627),"") -> 0.53613516 | H5: =IFERROR(MEDIAN('Статьи'!$O$5:$O$627),"") -> 0.97320146 | I5: =IFERROR(MEDIAN('Статьи'!$P$5:$P$627),"") -> 0.055204512 | J5: =IFERROR(MEDIAN('Статьи'!$Q$5:$Q$627),"") -> 0.010179645 | K5: =IFERROR(MEDIAN('Статьи'!$R$5:$R$627),"") -> 0.0040031383
A6: Ролики — все | B6: =COUNT('Ролики'!$F$5:$F$665) -> 661 | C6: =IFERROR(MEDIAN('Ролики'!$F$5:$F$665),"") -> 46418 | D6: =IFERROR(MEDIAN('Ролики'!$G$5:$G$665),"") -> 14153 | E6: =IFERROR(MEDIAN('Ролики'!$H$5:$H$665),"") -> 12724 | F6: =IFERROR(MEDIAN('Ролики'!$M$5:$M$665),"") -> 0.2970281 | G6: =IFERROR(MEDIAN('Ролики'!$N$5:$N$665),"") -> 0.99991357 | H6: =IFERROR(MEDIAN('Ролики'!$O$5:$O$665),"") -> 0.0040548767 | I6: =IFERROR(MEDIAN('Ролики'!$P$5:$P$665),"") -> 0.012606504 | J6: =IFERROR(MEDIAN('Ролики'!$Q$5:$Q$665),"") -> 0.00067249617 | K6: =IFERROR(MEDIAN('Ролики'!$R$5:$R$665),"") -> 0.00068729662
A7: Посты — все | B7: =COUNT('Посты'!$F$5:$F$373) -> 369 | C7: =IFERROR(MEDIAN('Посты'!$F$5:$F$373),"") -> 3102 | D7: =IFERROR(MEDIAN('Посты'!$G$5:$G$373),"") -> 222 | E7: =IFERROR(MEDIAN('Посты'!$H$5:$H$373),"") -> 233 | F7: =IFERROR(MEDIAN('Посты'!$M$5:$M$373),"") -> 0.069631031 | G7: =IFERROR(MEDIAN('Посты'!$N$5:$N$373),"") -> 0.99646643 | H7: =IFERROR(MEDIAN('Посты'!$O$5:$O$373),"") -> 0.54411765 | I7: =IFERROR(MEDIAN('Посты'!$P$5:$P$373),"") -> 0.13366337 | J7: =IFERROR(MEDIAN('Посты'!$Q$5:$Q$373),"") -> 0.020134228 | K7: =IFERROR(MEDIAN('Посты'!$R$5:$R$373),"") -> 0
A8: Статьи — 2023 | B8: =COUNT('Статьи'!$F$5:$F$56) -> 52 | C8: =IFERROR(MEDIAN('Статьи'!$F$5:$F$56),"") -> 74706.5 | D8: =IFERROR(MEDIAN('Статьи'!$G$5:$G$56),"") -> 3369.5 | E8: =IFERROR(MEDIAN('Статьи'!$H$5:$H$56),"") -> 1915 | F8: =IFERROR(MEDIAN('Статьи'!$M$5:$M$56),"") -> 0.040272355 | G8: =IFERROR(MEDIAN('Статьи'!$N$5:$N$56),"") -> 0.5862069 | H8: =IFERROR(MEDIAN('Статьи'!$O$5:$O$56),"") -> 0.96940727 | I8: =IFERROR(MEDIAN('Статьи'!$P$5:$P$56),"") -> 0.0535815 | J8: =IFERROR(MEDIAN('Статьи'!$Q$5:$Q$56),"") -> 0.0062215478 | K8: =IFERROR(MEDIAN('Статьи'!$R$5:$R$56),"") -> 0.0062674874
A9: Статьи — 2024 | B9: =COUNT('Статьи'!$F$57:$F$225) -> 169 | C9: =IFERROR(MEDIAN('Статьи'!$F$57:$F$225),"") -> 166341 | D9: =IFERROR(MEDIAN('Статьи'!$G$57:$G$225),"") -> 11208 | E9: =IFERROR(MEDIAN('Статьи'!$H$57:$H$225),"") -> 6076 | F9: =IFERROR(MEDIAN('Статьи'!$M$57:$M$225),"") -> 0.047701247 | G9: =IFERROR(MEDIAN('Статьи'!$N$57:$N$225),"") -> 0.54700728 | H9: =IFERROR(MEDIAN('Статьи'!$O$57:$O$225),"") -> 0.93809524 | I9: =IFERROR(MEDIAN('Статьи'!$P$57:$P$225),"") -> 0.049435028 | J9: =IFERROR(MEDIAN('Статьи'!$Q$57:$Q$225),"") -> 0.0098559515 | K9: =IFERROR(MEDIAN('Статьи'!$R$57:$R$225),"") -> 0.0045026607
A10: Статьи — 2025 | B10: =COUNT('Статьи'!$F$226:$F$465) -> 240 | C10: =IFERROR(MEDIAN('Статьи'!$F$226:$F$465),"") -> 327575 | D10: =IFERROR(MEDIAN('Статьи'!$G$226:$G$465),"") -> 25099 | E10: =IFERROR(MEDIAN('Статьи'!$H$226:$H$465),"") -> 12304.5 | F10: =IFERROR(MEDIAN('Статьи'!$M$226:$M$465),"") -> 0.063563112 | G10: =IFERROR(MEDIAN('Статьи'!$N$226:$N$465),"") -> 0.53487649 | H10: =IFERROR(MEDIAN('Статьи'!$O$226:$O$465),"") -> 1.0190826 | I10: =IFERROR(MEDIAN('Статьи'!$P$226:$P$465),"") -> 0.048111912 | J10: =IFERROR(MEDIAN('Статьи'!$Q$226:$Q$465),"") -> 0.00988042 | K10: =IFERROR(MEDIAN('Статьи'!$R$226:$R$465),"") -> 0.0038535675
A11: Статьи — 2026 | B11: =COUNT('Статьи'!$F$466:$F$627) -> 162 | C11: =IFERROR(MEDIAN('Статьи'!$F$466:$F$627),"") -> 53200.5 | D11: =IFERROR(MEDIAN('Статьи'!$G$466:$G$627),"") -> 2069.5 | E11: =IFERROR(MEDIAN('Статьи'!$H$466:$H$627),"") -> 954.5 | F11: =IFERROR(MEDIAN('Статьи'!$M$466:$M$627),"") -> 0.056578846 | G11: =IFERROR(MEDIAN('Статьи'!$N$466:$N$627),"") -> 0.51848848 | H11: =IFERROR(MEDIAN('Статьи'!$O$466:$O$627),"") -> 0.97133497 | I11: =IFERROR(MEDIAN('Статьи'!$P$466:$P$627),"") -> 0.075450135 | J11: =IFERROR(MEDIAN('Статьи'!$Q$466:$Q$627),"") -> 0.017843707 | K11: =IFERROR(MEDIAN('Статьи'!$R$466:$R$627),"") -> 0.003732471
A13: Показатели рассчитаны по формулам от исходных чисел выгрузки — при обновлении данных пересчитаются автоматически.

Sheet Статьи
A1: Статьи
A2: Все статьи канала. Индексы считаются внутри этого листа — статья сравнивается только с другими статьями того же периода.
A4: Дата публикации | B4: Час | C4: День недели | D4: Заголовок | E4: Ссылка | F4: Показы | G4: Открытия | H4: Дочитывания | I4: Время просмотра, мин | J4: Лайки | K4: Комментарии | L4: Подписки | M4: CTR (открытия/показы) | N4: Дочитываемость | O4: Минут на дочитывание | P4: Лайки / дочитывания | Q4: Комментарии / дочитывания | R4: Подписки / дочитывания | S4: Индекс CTR к периоду | T4: Индекс дочитываемости к периоду | U4: Индекс комментариев к периоду
A5: 45013.501 | B5: 12 | C5: вт | D5: Моя удачная борьба со стрессом | E5: ссылка | F5: 10922 | G5: 215 | H5: 154 | I5: 10 | J5: 25 | K5: 2 | L5: 1 | M5: =IFERROR(G5/F5,"") -> 0.019685039 | N5: =IFERROR(H5/G5,"") -> 0.71627907 | O5: =IFERROR(I5/H5,"") -> 0.064935065 | P5: =IFERROR(J5/H5,"") -> 0.16233766 | Q5: =IFERROR(K5/H5,"") -> 0.012987013 | R5: =IFERROR(L5/H5,"") -> 0.0064935065 | S5: =IFERROR(M5/MEDIAN(INDEX($M$5:$M$627,MATCH($A5-90,$A$5:$A$627,1)):INDEX($M$5:$M$627,MATCH($A5+90,$A$5:$A$627,1))),"") | T5: =IFERROR(N5/MEDIAN(INDEX($N$5:$N$627,MATCH($A5-90,$A$5:$A$627,1)):INDEX($N$5:$N$627,MATCH($A5+90,$A$5:$A$627,1))),"") | U5: =IFERROR(Q5/MEDIAN(INDEX($Q$5:$Q$627,MATCH($A5-90,$A$5:$A$627,1)):INDEX($Q$5:$Q$627,MATCH($A5+90,$A$5:$A$627,1))),"")
A6: 45020.75 | B6: 17 | C6: вт | D6: Сервировка стола | E6: ссылка | F6: 371572 | G6: 22787 | H6: 13180 | I6: 7251 | J6: 1029 | K6: 82 | L6: 210 | M6: =IFERROR(G6/F6,"") -> 0.061325934 | N6: =IFERROR(H6/G6,"") -> 0.57839996 | O6: =IFERROR(I6/H6,"") -> 0.55015175 | P6: =IFERROR(J6/H6,"") -> 0.078072838 | Q6: =IFERROR(K6/H6,"") -> 0.0062215478 | R6: =IFERROR(L6/H6,"") -> 0.015933232 | S6: =IFERROR(M6/MEDIAN(INDEX($M$5:$M$627,MATCH($A6-90,$A$5:$A$627,1)):INDEX($M$5:$M$627,MATCH($A6+90,$A$5:$A$627,1))),"") | T6: =IFERROR(N6/MEDIAN(INDEX($N$5:$N$627,MATCH($A6-90,$A$5:$A$627,1)):INDEX($N$5:$N$627,MATCH($A6+90,$A$5:$A$627,1))),"") | U6: =IFERROR(Q6/MEDIAN(INDEX($Q$5:$Q$627,MATCH($A6-90,$A$5:$A$627,1)):INDEX($Q$5:$Q$627,MATCH($A6+90,$A$5:$A$627,1))),"")
A7: 45038.481 | B7: 11 | C7: сб | D7: Этот лайфхак столового этикета всегда в ваших руках | E7: ссылка | F7: 40126 | G7: 1754 | H7: 1205 | I7: 495 | J7: 183 | K7: 3 | L7: 13 | M7: =IFERROR(G7/F7,"") -> 0.043712306 | N7: =IFERROR(H7/G7,"") -> 0.68700114 | O7: =IFERROR(I7/H7,"") -> 0.41078838 | P7: =IFERROR(J7/H7,"") -> 0.15186722 | Q7: =IFERROR(K7/H7,"") -> 0.0024896266 | R7: =IFERROR(L7/H7,"") -> 0.010788382 | S7: =IFERROR(M7/MEDIAN(INDEX($M$5:$M$627,MATCH($A7-90,$A$5:$A$627,1)):INDEX($M$5:$M$627,MATCH($A7+90,$A$5:$A$627,1))),"") | T7: =IFERROR(N7/MEDIAN(INDEX($N$5:$N$627,MATCH($A7-90,$A$5:$A$627,1)):INDEX($N$5:$N$627,MATCH($A7+90,$A$5:$A$627,1))),"") | U7: =IFERROR(Q7/MEDIAN(INDEX($Q$5:$Q$627,MATCH($A7-90,$A$5:$A$627,1)):INDEX($Q$5:$Q$627,MATCH($A7+90,$A$5:$A$627,1))),"")
A8: 45073.723 | B8: 17 | C8: сб | D8: Формальный и неформальный деловой дресс-код | E8: ссылка | F8: 219296 | G8: 9471 | H8: 5271 | I8: 5471 | J8: 164 | K8: 15 | L8: 37 | M8: =IFERROR(G8/F8,"") -> 0.043188202 | N8: =IFERROR(H8/G8,"") -> 0.55654102 | O8: =IFERROR(I8/H8,"") -> 1.0379435 | P8: =IFERROR(J8/H8,"") -> 0.031113641 | Q8: =IFERROR(K8/H8,"") -> 0.0028457598 | R8: =IFERROR(L8/H8,"") -> 0.0070195409 | S8: =IFERROR(M8/MEDIAN(INDEX($M$5:$M$627,MATCH($A8-90,$A$5:$A$627,1)):INDEX($M$5:$M$627,MATCH($A8+90,$A$5:$A$627,1))),"") | T8: =IFERROR(N8/MEDIAN(INDEX($N$5:$N$627,MATCH($A8-90,$A$5:$A$627,1)):INDEX($N$5:$N$627,MATCH($A8+90,$A$5:$A$627,1))),"") | U8: =IFERROR(Q8/MEDIAN(INDEX($Q$5:$Q$627,MATCH($A8-90,$A$5:$A$627,1)):INDEX($Q$5:$Q$627,MATCH($A8+90,$A$5:$A$627,1))),"")
A9: 45147.664 | B9: 15 | C9: ср | D9: Этикет: ваш личный компас | E9: ссылка | F9: 12515 | G9: 451 | H9: 288 | I9: 315 | J9: 77 | K9: 3 | L9: 5 | M9: =IFERROR(G9/F9,"") -> 0.036036756 | N9: =IFERROR(H9/G9,"") -> 0.63858093 | O9: =IFERROR(I9/H9,"") -> 1.09375 | P9: =IFERROR(J9/H9,"") -> 0.26736111 | Q9: =IFERROR(K9/H9,"") -> 0.010416667 | R9: =IFERROR(L9/H9,"") -> 0.017361111 | S9: =IFERROR(M9/MEDIAN(INDEX($M$5:$M$627,MATCH($A9-90,$A$5:$A$627,1)):INDEX($M$5:$M$627,MATCH($A9+90,$A$5:$A$627,1))),"") -> 0.89327561 | T9: =IFERROR(N9/MEDIAN(INDEX($N$5:$N$627,MATCH($A9-90,$A$5:$A$627,1)):INDEX($N$5:$N$627,MATCH($A9+90,$A$5:$A$627,1))),"") -> 1.1946013 | U9: =IFERROR(Q9/MEDIAN(INDEX($Q$5:$Q$627,MATCH($A9-90,$A$5:$A$627,1)):INDEX($Q$5:$Q$627,MATCH($A9+90,$A$5:$A$627,1))),"") -> 3.6323973
A10: 45148.482 | B10: 11 | C10: чт | D10: Страх или безответственность? | E10: ссылка | F10: 199045 | G10: 11970 | H10: 5406 | I10: 6001 | J10: 281 | K10: 21 | L10: 33 | M10: =IFERROR(G10/F10,"") -> 0.060137155 | N10: =IFERROR(H10/G10,"") -> 0.45162907 | O10: =IFERROR(I10/H10,"") -> 1.1100629 | P10: =IFERROR(J10/H10,"") -> 0.051979282 | Q10: =IFERROR(K10/H10,"") -> 0.0038845727 | R10: =IFERROR(L10/H10,"") -> 0.0061043285 | S10: =IFERROR(M10/MEDIAN(INDEX($M$5:$M$627,MATCH($A10-90,$A$5:$A$627,1)):INDEX($M$5:$M$627,MATCH($A10+90,$A$5:$A$627,1))),"") -> 1.4938017 | T10: =IFERROR(N10/MEDIAN(INDEX($N$5:$N$627,MATCH($A10-90,$A$5:$A$627,1)):INDEX($N$5:$N$627,MATCH($A10+90,$A$5:$A$627,1))),"") -> 0.83720422 | U10: =IFERROR(Q10/MEDIAN(INDEX($Q$5:$Q$627,MATCH($A10-90,$A$5:$A$627,1)):INDEX($Q$5:$Q$627,MATCH($A10+90,$A$5:$A$627,1))),"") -> 1.1505952
A11: 45154.57 | B11: 13 | C11: ср | D11: Управление стрессом на рабочем месте: практические советы | E11: ссылка | F11: 132789 | G11: 4838 | H11: 2057 | I11: 2047 | J11: 118 | K11: 5 | L11: 18 | M11: =IFERROR(G11/F11,"") -> 0.036433741 | N11: =IFERROR(H11/G11,"") -> 0.42517569 | O11: =IFERROR(I11/H11,"") -> 0.99513855 | P11: =IFERROR(J11/H11,"") -> 0.057365095 | Q11: =IFERROR(K11/H11,"") -> 0.0024307244 | R11: =IFERROR(L11/H11,"") -> 0.0087506077 | S11: =IFERROR(M11/MEDIAN(INDEX($M$5:$M$627,MATCH($A11-90,$A$5:$A$627,1)):INDEX($M$5:$M$627,MATCH($A11+90,$A$5:$A$627,1))),"") -> 0.90691389 | T11: =IFERROR(N11/MEDIAN(INDEX($N$5:$N$627,MATCH($A11-90,$A$5:$A$627,1)):INDEX($N$5:$N$627,MATCH($A11+90,$A$5:$A$627,1))),"") -> 0.78108119 | U11: =IFERROR(Q11/MEDIAN(INDEX($Q$5:$Q$627,MATCH($A11-90,$A$5:$A$627,1)):INDEX($Q$5:$Q$627,MATCH($A11+90,$A$5:$A$627,1))),"") -> 0.6257379
A12: 45157.538 | B12: 12 | C12: сб | D12: Этикет в музее: Путеводитель по уважительному взаимодействию с искусством | E12: ссылка | F12: 19075 | G12: 709 | H12: 379 | I12: 347 | J12: 98 | K12: 16 | L12: 4 | M12: =IFERROR(G12/F12,"") -> 0.037169069 | N12: =IFERROR(H12/G12,"") -> 0.53455571 | O12: =IFERROR(I12/H12,"") -> 0.91556728 | P12: =IFERROR(J12/H12,"") -> 0.2585752 | Q12: =IFERROR(K12/H12,"") -> 0.042216359 | R12: =IFERROR(L12/H12,"") -> 0.01055409 | S12: =IFERROR(M12/MEDIAN(INDEX($M$5:$M$627,MATCH($A12-90,$A$5:$A$627,1)):INDEX($M$5:$M$627,MATCH($A12+90,$A$5:$A$627,1))),"") -> 0.95791943 | T12: =IFERROR(N12/MEDIAN(INDEX($N$5:$N$627,MATCH($A12-90,$A$5:$A$627,1)):INDEX($N$5:$N$627,MATCH($A12+90,$A$5:$A$627,1))),"") -> 0.9909289 | U12: =IFERROR(Q12/MEDIAN(INDEX($Q$5:$Q$627,MATCH($A12-90,$A$5:$A$627,1)):INDEX($Q$5:$Q$627,MATCH($A12+90,$A$5:$A$627,1))),"") -> 10.661313
A13: 45209.697 | B13: 16 | C13: вт | D13: Шпаргалка: Как ответить на вакансию и произвести впечатление | E13: ссылка | F13: 279905 | G13: 11292 | H13: 4480 | I13: 6461 | J13: 122 | K13: 32 | L13: 83 | M13: =IFERROR(G13/F13,"") -> 0.040342259 | N13: =IFERROR(H13/G13,"") -> 0.39674106 | O13: =IFERROR(I13/H13,"") -> 1.4421875 | P13: =IFERROR(J13/H13,"") -> 0.027232143 | Q13: =IFERROR(K13/H13,"") -> 0.0071428571 | R13: =IFERROR(L13/H13,"") -> 0.018526786 | S13: =IFERROR(M13/MEDIAN(INDEX($M$5:$M$627,MATCH($A13-90,$A$5:$A$627,1)):INDEX($M$5:$M$627,MATCH($A13+90,$A$5:$A$627,1))),"") -> 1.002969 | T13: =IFERROR(N13/MEDIAN(INDEX($N$5:$N$627,MATCH($A13-90,$A$5:$A$627,1)):INDEX($N$5:$N$627,MATCH($A13+90,$A$5:$A$627,1))),"") -> 0.67518203 | U13: =IFERROR(Q13/MEDIAN(INDEX($Q$5:$Q$627,MATCH($A13-90,$A$5:$A$627,1)):INDEX($Q$5:$Q$627,MATCH($A13+90,$A$5:$A$627,1))),"") -> 1.1005197
A14: 45211.736 | B14: 17 | C14: чт | D14: Эмоциональное равновесие: как справляться с грубостью и сохранять спокойствие | E14: ссылка | F14: 761072 | G14: 21093 | H14: 8935 | I14: 5393 | J14: 334 | K14: 75 | L14: 56 | M14: =IFERROR(G14/F14,"") -> 0.027714855 | N14: =IFERROR(H14/G14,"") -> 0.42360025 | O14: =IFERROR(I14/H14,"") -> 0.60358142 | P14: =IFERROR(J14/H14,"") -> 0.037381086 | Q14: =IFERROR(K14/H14,"") -> 0.0083939564 | R14: =IFERROR(L14/H14,"") -> 0.0062674874 | S14: =IFERROR(M14/MEDIAN(INDEX($M$5:$M$627,MATCH($A14-90,$A$5:$A$627,1)):INDEX($M$5:$M$627,MATCH($A14+90,$A$5:$A$627,1))),"") -> 0.6881856 | T14: =IFERROR(N14/MEDIAN(INDEX($N$5:$N$627,MATCH($A14-90,$A$5:$A$627,1)):INDEX($N$5:$N$627,MATCH($A14+90,$A$5:$A$627,1))),"") -> 0.71917909 | U14: =IFERROR(Q14/MEDIAN(INDEX($Q$5:$Q$627,MATCH($A14-90,$A$5:$A$627,1)):INDEX($Q$5:$Q$627,MATCH($A14+90,$A$5:$A$627,1))),"") -> 1.3085889
A15: 45213.827 | B15: 19 | C15: сб | D15: Как правильно сидеть даме по этикету: 3 лучших варианта | E15: ссылка | F15: 1359452 | G15: 91932 | H15: 68014 | I15: 47005 | J15: 2202 | K15: 150 | L15: 243 | M15: =IFERROR(G15/F15,"") -> 0.067624307 | N15: =IFERROR(H15/G15,"") -> 0.73982944 | O15: =IFERROR(I15/H15,"") -> 0.69110771 | P15: =IFERROR(J15/H15,"") -> 0.032375687 | Q15: =IFERROR(K15/H15,"") -> 0.0022054283 | R15: =IFERROR(L15/H15,"") -> 0.0035727938 | S15: =IFERROR(M15/MEDIAN(INDEX($M$5:$M$627,MATCH($A15-90,$A$5:$A$627,1)):INDEX($M$5:$M$627,MATCH($A15+90,$A$5:$A$627,1))),"") -> 1.6812416 | T15: =IFERROR(N15/MEDIAN(INDEX($N$5:$N$627,MATCH($A15-90,$A$5:$A$627,1)):INDEX($N$5:$N$627,MATCH($A15+90,$A$5:$A$627,1))),"") -> 1.2590568 | U15: =IFERROR(Q15/MEDIAN(INDEX($Q$5:$Q$627,MATCH($A15-90,$A$5:$A$627,1)):INDEX($Q$5:$Q$627,MATCH($A15+90,$A$5:$A$627,1))),"") -> 0.35286312
A16: 45215.858 | B16: 20 | C16: пн | D16: Этикет под зонтом | E16: ссылка | F16: 0 | G16: 0 | H16: 0 | I16: 4 | J16: 0 | K16: 0 | L16: 0 | M16: =IFERROR(G16/F16,"") | N16: =IFERROR(H16/G16,"") | O16: =IFERROR(I16/H16,"") | P16: =IFERROR(J16/H16,"") | Q16: =IFERROR(K16/H16,"") | R16: =IFERROR(L16/H16,"") | S16: =IFERROR(M16/MEDIAN(INDEX($M$5:$M$627,MATCH($A16-90,$A$5:$A$627,1)):INDEX($M$5:$M$627,MATCH($A16+90,$A$5:$A$627,1))),"") -> 0 | T16: =IFERROR(N16/MEDIAN(INDEX($N$5:$N$627,MATCH($A16-90,$A$5:$A$627,1)):INDEX($N$5:$N$627,MATCH($A16+90,$A$5:$A$627,1))),"") -> 0 | U16: =IFERROR(Q16/MEDIAN(INDEX($Q$5:$Q$627,MATCH($A16-90,$A$5:$A$627,1)):INDEX($Q$5:$Q$627,MATCH($A16+90,$A$5:$A$627,1))),"") -> 0
... A627: 46227.572 | B627: 13 | C627: пт | D627: Лицемерная помощь | E627: ссылка | F627: 4285 | G627: 746 | H627: 432 | I627: 0 | J627: 60 | K627: 234 | L627: 0 | M627: =IFERROR(G627/F627,"") -> 0.17409568 | N627: =IFERROR(H627/G627,"") -> 0.57908847 | O627: =IFERROR(I627/H627,"") -> 0 | P627: =IFERROR(J627/H627,"") -> 0.13888889 | Q627: =IFERROR(K627/H627,"") -> 0.54166667 | R627: =IFERROR(L627/H627,"") -> 0 | S627: =IFERROR(M627/MEDIAN(INDEX($M$5:$M$627,MATCH($A627-90,$A$5:$A$627,1)):INDEX($M$5:$M$627,MATCH($A627+90,$A$5:$A$627,1))),"") -> 2.4373396 | T627: =IFERROR(N627/MEDIAN(INDEX($N$5:$N$627,MATCH($A627-90,$A$5:$A$627,1)):INDEX($N$5:$N$627,MATCH($A627+90,$A$5:$A$627,1))),"") -> 1.1013148 | U627: =IFERROR(Q627/MEDIAN(INDEX($Q$5:$Q$627,MATCH($A627-90,$A$5:$A$627,1)):INDEX($Q$5:$Q$627,MATCH($A627+90,$A$5:$A$627,1))),"") -> 10.170398

Sheet Ролики
A1: Ролики
A2: Ролики. Отдельный лист: их воронка устроена иначе, сравнение со статьями некорректно.
A4: Дата публикации | B4: Час | C4: День недели | D4: Заголовок | E4: Ссылка | F4: Показы | G4: Открытия | H4: Дочитывания | I4: Время просмотра, мин | J4: Лайки | K4: Комментарии | L4: Подписки | M4: CTR (открытия/показы) | N4: Дочитываемость | O4: Минут на дочитывание | P4: Лайки / дочитывания | Q4: Комментарии / дочитывания | R4: Подписки / дочитывания | S4: Индекс CTR к периоду | T4: Индекс дочитываемости к периоду | U4: Индекс комментариев к периоду
A5: 44960.839 | B5: 20 | C5: пт | D5: Проверьте свои знания в этикете 🙌🏻 | E5: ссылка | F5: 23914 | G5: 12583 | H5: 12589 | I5: 25 | J5: 267 | K5: 13 | L5: 34 | M5: =IFERROR(G5/F5,"") -> 0.52617713 | N5: =IFERROR(H5/G5,"") -> 1.0004768 | O5: =IFERROR(I5/H5,"") -> 0.0019858607 | P5: =IFERROR(J5/H5,"") -> 0.021208992 | Q5: =IFERROR(K5/H5,"") -> 0.0010326475 | R5: =IFERROR(L5/H5,"") -> 0.0027007705 | S5: =IFERROR(M5/MEDIAN(INDEX($M$5:$M$665,MATCH($A5-90,$A$5:$A$665,1)):INDEX($M$5:$M$665,MATCH($A5+90,$A$5:$A$665,1))),"") | T5: =IFERROR(N5/MEDIAN(INDEX($N$5:$N$665,MATCH($A5-90,$A$5:$A$665,1)):INDEX($N$5:$N$665,MATCH($A5+90,$A$5:$A$665,1))),"") | U5: =IFERROR(Q5/MEDIAN(INDEX($Q$5:$Q$665,MATCH($A5-90,$A$5:$A$665,1)):INDEX($Q$5:$Q$665,MATCH($A5+90,$A$5:$A$665,1))),"")
A6: 44961.546 | B6: 13 | C6: сб | D6: Несколько правил столового этикета🍽 #этикет #этикетзастолом #столовыйэтикет #правилаэтикета | E6: ссылка | F6: 4422 | G6: 2420 | H6: 2427 | I6: 113 | J6: 152 | K6: 4 | L6: 2 | M6: =IFERROR(G6/F6,"") -> 0.54726368 | N6: =IFERROR(H6/G6,"") -> 1.0028926 | O6: =IFERROR(I6/H6,"") -> 0.046559539 | P6: =IFERROR(J6/H6,"") -> 0.06262876 | Q6: =IFERROR(K6/H6,"") -> 0.0016481253 | R6: =IFERROR(L6/H6,"") -> 0.00082406263 | S6: =IFERROR(M6/MEDIAN(INDEX($M$5:$M$665,MATCH($A6-90,$A$5:$A$665,1)):INDEX($M$5:$M$665,MATCH($A6+90,$A$5:$A$665,1))),"") | T6: =IFERROR(N6/MEDIAN(INDEX($N$5:$N$665,MATCH($A6-90,$A$5:$A$665,1)):INDEX($N$5:$N$665,MATCH($A6+90,$A$5:$A$665,1))),"") | U6: =IFERROR(Q6/MEDIAN(INDEX($Q$5:$Q$665,MATCH($A6-90,$A$5:$A$665,1)):INDEX($Q$5:$Q$665,MATCH($A6+90,$A$5:$A$665,1))),"")
A7: 44961.75 | B7: 18 | C7: сб | D7: НЕ деловая причёска ❌ #правилаэтикета #этикет #деловойстиль #деловойэтикет #деловойобраз #деловойимидж | E7: ссылка | F7: 4089 | G7: 2091 | H7: 2086 | I7: 10 | J7: 164 | K7: 5 | L7: 4 | M7: =IFERROR(G7/F7,"") -> 0.51137197 | N7: =IFERROR(H7/G7,"") -> 0.9976088 | O7: =IFERROR(I7/H7,"") -> 0.0047938639 | P7: =IFERROR(J7/H7,"") -> 0.078619367 | Q7: =IFERROR(K7/H7,"") -> 0.0023969319 | R7: =IFERROR(L7/H7,"") -> 0.0019175455 | S7: =IFERROR(M7/MEDIAN(INDEX($M$5:$M$665,MATCH($A7-90,$A$5:$A$665,1)):INDEX($M$5:$M$665,MATCH($A7+90,$A$5:$A$665,1))),"") | T7: =IFERROR(N7/MEDIAN(INDEX($N$5:$N$665,MATCH($A7-90,$A$5:$A$665,1)):INDEX($N$5:$N$665,MATCH($A7+90,$A$5:$A$665,1))),"") | U7: =IFERROR(Q7/MEDIAN(INDEX($Q$5:$Q$665,MATCH($A7-90,$A$5:$A$665,1)):INDEX($Q$5:$Q$665,MATCH($A7+90,$A$5:$A$665,1))),"")
A8: 44962.5 | B8: 12 | C8: вс | D8: Несколько помад, которые вас никогда не подведут #помада #помададлягуб #губнаяпомада #этикет #деловойстиль #деловойимидж | E8: ссылка | F8: 2525 | G8: 1497 | H8: 1499 | I8: 9 | J8: 114 | K8: 3 | L8: 2 | M8: =IFERROR(G8/F8,"") -> 0.59287129 | N8: =IFERROR(H8/G8,"") -> 1.001336 | O8: =IFERROR(I8/H8,"") -> 0.0060040027 | P8: =IFERROR(J8/H8,"") -> 0.0760507 | Q8: =IFERROR(K8/H8,"") -> 0.0020013342 | R8: =IFERROR(L8/H8,"") -> 0.0013342228 | S8: =IFERROR(M8/MEDIAN(INDEX($M$5:$M$665,MATCH($A8-90,$A$5:$A$665,1)):INDEX($M$5:$M$665,MATCH($A8+90,$A$5:$A$665,1))),"") | T8: =IFERROR(N8/MEDIAN(INDEX($N$5:$N$665,MATCH($A8-90,$A$5:$A$665,1)):INDEX($N$5:$N$665,MATCH($A8+90,$A$5:$A$665,1))),"") | U8: =IFERROR(Q8/MEDIAN(INDEX($Q$5:$Q$665,MATCH($A8-90,$A$5:$A$665,1)):INDEX($Q$5:$Q$665,MATCH($A8+90,$A$5:$A$665,1))),"")
A9: 44962.75 | B9: 17 | C9: вс | D9: Какие оттенки помад допустимы в деловом образе? #этикет #деловойстиль #деловойэтикет #деловойобраз #деловойимидж #помада #помададлягуб #губнаяпомада | E9: ссылка | F9: 21490 | G9: 7048 | H9: 7046 | I9: 5 | J9: 139 | K9: 4 | L9: 13 | M9: =IFERROR(G9/F9,"") -> 0.3279665 | N9: =IFERROR(H9/G9,"") -> 0.99971623 | O9: =IFERROR(I9/H9,"") -> 0.00070962248 | P9: =IFERROR(J9/H9,"") -> 0.019727505 | Q9: =IFERROR(K9/H9,"") -> 0.00056769798 | R9: =IFERROR(L9/H9,"") -> 0.0018450185 | S9: =IFERROR(M9/MEDIAN(INDEX($M$5:$M$665,MATCH($A9-90,$A$5:$A$665,1)):INDEX($M$5:$M$665,MATCH($A9+90,$A$5:$A$665,1))),"") | T9: =IFERROR(N9/MEDIAN(INDEX($N$5:$N$665,MATCH($A9-90,$A$5:$A$665,1)):INDEX($N$5:$N$665,MATCH($A9+90,$A$5:$A$665,1))),"") | U9: =IFERROR(Q9/MEDIAN(INDEX($Q$5:$Q$665,MATCH($A9-90,$A$5:$A$665,1)):INDEX($Q$5:$Q$665,MATCH($A9+90,$A$5:$A$665,1))),"")
A10: 44963.5 | B10: 11 | C10: пн | D10: Проверьте свои знания в этикете 🙌🏻 #деловойстиль #этикет #деловойимидж #правилаэтикета #деловойэтикет #деловойобраз #приветствие | E10: ссылка | F10: 28486 | G10: 12811 | H10: 12814 | I10: 10 | J10: 191 | K10: 13 | L10: 9 | M10: =IFERROR(G10/F10,"") -> 0.44972969 | N10: =IFERROR(H10/G10,"") -> 1.0002342 | O10: =IFERROR(I10/H10,"") -> 0.00078039644 | P10: =IFERROR(J10/H10,"") -> 0.014905572 | Q10: =IFERROR(K10/H10,"") -> 0.0010145154 | R10: =IFERROR(L10/H10,"") -> 0.0007023568 | S10: =IFERROR(M10/MEDIAN(INDEX($M$5:$M$665,MATCH($A10-90,$A$5:$A$665,1)):INDEX($M$5:$M$665,MATCH($A10+90,$A$5:$A$665,1))),"") | T10: =IFERROR(N10/MEDIAN(INDEX($N$5:$N$665,MATCH($A10-90,$A$5:$A$665,1)):INDEX($N$5:$N$665,MATCH($A10+90,$A$5:$A$665,1))),"") | U10: =IFERROR(Q10/MEDIAN(INDEX($Q$5:$Q$665,MATCH($A10-90,$A$5:$A$665,1)):INDEX($Q$5:$Q$665,MATCH($A10+90,$A$5:$A$665,1))),"")
A11: 44964.616 | B11: 14 | C11: вт | D11: Почему этикет не любит слово здравствуйте? #этикет #деловойстиль #деловойимидж #правилаэтикета #деловойобраз #приветствие | E11: ссылка | F11: 29810 | G11: 18272 | H11: 18271 | I11: 5 | J11: 201 | K11: 31 | L11: 89 | M11: =IFERROR(G11/F11,"") -> 0.61294867 | N11: =IFERROR(H11/G11,"") -> 0.99994527 | O11: =IFERROR(I11/H11,"") -> 0.00027365771 | P11: =IFERROR(J11/H11,"") -> 0.01100104 | Q11: =IFERROR(K11/H11,"") -> 0.0016966778 | R11: =IFERROR(L11/H11,"") -> 0.0048711072 | S11: =IFERROR(M11/MEDIAN(INDEX($M$5:$M$665,MATCH($A11-90,$A$5:$A$665,1)):INDEX($M$5:$M$665,MATCH($A11+90,$A$5:$A$665,1))),"") | T11: =IFERROR(N11/MEDIAN(INDEX($N$5:$N$665,MATCH($A11-90,$A$5:$A$665,1)):INDEX($N$5:$N$665,MATCH($A11+90,$A$5:$A$665,1))),"") | U11: =IFERROR(Q11/MEDIAN(INDEX($Q$5:$Q$665,MATCH($A11-90,$A$5:$A$665,1)):INDEX($Q$5:$Q$665,MATCH($A11+90,$A$5:$A$665,1))),"")
A12: 44964.666 | B12: 15 | C12: вт | D12: Как правильно здороваться? #этикет #деловойстиль #деловоеобщение #этикетобщения #деловыепереговоры #деловаярепутация | E12: ссылка | F12: 60880 | G12: 26764 | H12: 26762 | I12: 4 | J12: 284 | K12: 35 | L12: 55 | M12: =IFERROR(G12/F12,"") -> 0.43961892 | N12: =IFERROR(H12/G12,"") -> 0.99992527 | O12: =IFERROR(I12/H12,"") -> 0.00014946566 | P12: =IFERROR(J12/H12,"") -> 0.010612062 | Q12: =IFERROR(K12/H12,"") -> 0.0013078245 | R12: =IFERROR(L12/H12,"") -> 0.0020551528 | S12: =IFERROR(M12/MEDIAN(INDEX($M$5:$M$665,MATCH($A12-90,$A$5:$A$665,1)):INDEX($M$5:$M$665,MATCH($A12+90,$A$5:$A$665,1))),"") | T12: =IFERROR(N12/MEDIAN(INDEX($N$5:$N$665,MATCH($A12-90,$A$5:$A$665,1)):INDEX($N$5:$N$665,MATCH($A12+90,$A$5:$A$665,1))),"") | U12: =IFERROR(Q12/MEDIAN(INDEX($Q$5:$Q$665,MATCH($A12-90,$A$5:$A$665,1)):INDEX($Q$5:$Q$665,MATCH($A12+90,$A$5:$A$665,1))),"")
A13: 44965.424 | B13: 10 | C13: ср | D13: Нежелательные звонки #этикет #деловойстиль #деловойимидж #правилаэтикета #деловойэтикет #этикетобщения #деловыепереговоры #звонокпотелефону | E13: ссылка | F13: 4523 | G13: 2419 | H13: 2414 | I13: 29 | J13: 113 | K13: 8 | L13: 2 | M13: =IFERROR(G13/F13,"") -> 0.53482202 | N13: =IFERROR(H13/G13,"") -> 0.99793303 | O13: =IFERROR(I13/H13,"") -> 0.012013256 | P13: =IFERROR(J13/H13,"") -> 0.046810273 | Q13: =IFERROR(K13/H13,"") -> 0.0033140017 | R13: =IFERROR(L13/H13,"") -> 0.00082850041 | S13: =IFERROR(M13/MEDIAN(INDEX($M$5:$M$665,MATCH($A13-90,$A$5:$A$665,1)):INDEX($M$5:$M$665,MATCH($A13+90,$A$5:$A$665,1))),"") | T13: =IFERROR(N13/MEDIAN(INDEX($N$5:$N$665,MATCH($A13-90,$A$5:$A$665,1)):INDEX($N$5:$N$665,MATCH($A13+90,$A$5:$A$665,1))),"") | U13: =IFERROR(Q13/MEDIAN(INDEX($Q$5:$Q$665,MATCH($A13-90,$A$5:$A$665,1)):INDEX($Q$5:$Q$665,MATCH($A13+90,$A$5:$A$665,1))),"")
A14: 44965.584 | B14: 14 | C14: ср | D14: Наша речь - отражение нас самих #этикет #деловойстиль #деловойимидж #правилаэтикета #деловойобраз #деловойэтикет #деловыепереговоры #деловаярепутация #этикетобщения #правильнаяречь #грамотнаяречь | E14: ссылка | F14: 1909 | G14: 1168 | H14: 1147 | I14: 9 | J14: 91 | K14: 7 | L14: 13 | M14: =IFERROR(G14/F14,"") -> 0.61183866 | N14: =IFERROR(H14/G14,"") -> 0.98202055 | O14: =IFERROR(I14/H14,"") -> 0.0078465562 | P14: =IFERROR(J14/H14,"") -> 0.079337402 | Q14: =IFERROR(K14/H14,"") -> 0.0061028771 | R14: =IFERROR(L14/H14,"") -> 0.011333915 | S14: =IFERROR(M14/MEDIAN(INDEX($M$5:$M$665,MATCH($A14-90,$A$5:$A$665,1)):INDEX($M$5:$M$665,MATCH($A14+90,$A$5:$A$665,1))),"") | T14: =IFERROR(N14/MEDIAN(INDEX($N$5:$N$665,MATCH($A14-90,$A$5:$A$665,1)):INDEX($N$5:$N$665,MATCH($A14+90,$A$5:$A$665,1))),"") | U14: =IFERROR(Q14/MEDIAN(INDEX($Q$5:$Q$665,MATCH($A14-90,$A$5:$A$665,1)):INDEX($Q$5:$Q$665,MATCH($A14+90,$A$5:$A$665,1))),"")
A15: 44965.667 | B15: 15 | C15: ср | D15: Умение слушать 👂🏻 #этикет #этикетобщения #правилаэтикета #деловойэтикет #деловоеобщение #деловыекоммуникации #деловыеотношения #деловыепереговоры | E15: ссылка | F15: 6329 | G15: 2980 | H15: 2978 | I15: 7 | J15: 110 | K15: 2 | L15: 7 | M15: =IFERROR(G15/F15,"") -> 0.47084848 | N15: =IFERROR(H15/G15,"") -> 0.99932886 | O15: =IFERROR(I15/H15,"") -> 0.0023505709 | P15: =IFERROR(J15/H15,"") -> 0.036937542 | Q15: =IFERROR(K15/H15,"") -> 0.00067159167 | R15: =IFERROR(L15/H15,"") -> 0.0023505709 | S15: =IFERROR(M15/MEDIAN(INDEX($M$5:$M$665,MATCH($A15-90,$A$5:$A$665,1)):INDEX($M$5:$M$665,MATCH($A15+90,$A$5:$A$665,1))),"") | T15: =IFERROR(N15/MEDIAN(INDEX($N$5:$N$665,MATCH($A15-90,$A$5:$A$665,1)):INDEX($N$5:$N$665,MATCH($A15+90,$A$5:$A$665,1))),"") | U15: =IFERROR(Q15/MEDIAN(INDEX($Q$5:$Q$665,MATCH($A15-90,$A$5:$A$665,1)):INDEX($Q$5:$Q$665,MATCH($A15+90,$A$5:$A$665,1))),"")
A16: 44965.75 | B16: 17 | C16: ср | D16: Слова "паразиты" #грамотнаяречь #правильнаяречь #красиваяречь #правилаэтикета #этикет #деловыепереговоры #деловыеотношения #деловойэтикет #деловойимидж | E16: ссылка | F16: 9857 | G16: 4488 | H16: 4486 | I16: 8 | J16: 180 | K16: 11 | L16: 20 | M16: =IFERROR(G16/F16,"") -> 0.45531095 | N16: =IFERROR(H16/G16,"") -> 0.99955437 | O16: =IFERROR(I16/H16,"") -> 0.0017833259 | P16: =IFERROR(J16/H16,"") -> 0.040124833 | Q16: =IFERROR(K16/H16,"") -> 0.0024520731 | R16: =IFERROR(L16/H16,"") -> 0.0044583148 | S16: =IFERROR(M16/MEDIAN(INDEX($M$5:$M$665,MATCH($A16-90,$A$5:$A$665,1)):INDEX($M$5:$M$665,MATCH($A16+90,$A$5:$A$665,1))),"") | T16: =IFERROR(N16/MEDIAN(INDEX($N$5:$N$665,MATCH($A16-90,$A$5:$A$665,1)):INDEX($N$5:$N$665,MATCH($A16+90,$A$5:$A$665,1))),"") | U16: =IFERROR(Q16/MEDIAN(INDEX($Q$5:$Q$665,MATCH($A16-90,$A$5:$A$665,1)):INDEX($Q$5:$Q$665,MATCH($A16+90,$A$5:$A$665,1))),"")
... A109: 45035.583 | B109: 13 | C109: ср | D109: Уважаемые пешеходы! #правилаэтикета #этикет #деловоеобщение #деловойэтикет #деловаярепутация #общественныеместа #этикетобщения | E109: ссылка | F109: 117386 | G109: 22425 | H109: 22420 | I109: 5 | J109: 305 | K109: 29 | L109: 21 | M109: =IFERROR(G109/F109,"") -> 0.19103641 | N109: =IFERROR(H109/G109,"") -> 0.99977703 | O109: =IFERROR(I109/H109,"") -> 0.00022301517 | P109: =IFERROR(J109/H109,"") -> 0.013603925 | Q109: =IFERROR(K109/H109,"") -> 0.001293488 | R109: =IFERROR(L109/H109,"") -> 0.00093666369 | S109: =IFERROR(M109/MEDIAN(INDEX($M$5:$M$665,MATCH($A109-90,$A$5:$A$665,1)):INDEX($M$5:$M$665,MATCH($A109+90,$A$5:$A$665,1))),"") | T109: =IFERROR(N109/MEDIAN(INDEX($N$5:$N$665,MATCH($A109-90,$A$5:$A$665,1)):INDEX($N$5:$N$665,MATCH($A109+90,$A$5:$A$665,1))),"") | U109: =IFERROR(Q109/MEDIAN(INDEX($Q$5:$Q$665,MATCH($A109-90,$A$5:$A$665,1)):INDEX($Q$5:$Q$665,MATCH($A109+90,$A$5:$A$665,1))),"")
A110: 45036.263 | B110: 6 | C110: чт | E110: ссылка | F110: 78383 | G110: 15586 | H110: 15582 | I110: 3 | J110: 204 | K110: 24 | L110: 18 | M110: =IFERROR(G110/F110,"") -> 0.19884414 | N110: =IFERROR(H110/G110,"") -> 0.99974336 | O110: =IFERROR(I110/H110,"") -> 0.00019252984 | P110: =IFERROR(J110/H110,"") -> 0.013092029 | Q110: =IFERROR(K110/H110,"") -> 0.0015402387 | R110: =IFERROR(L110/H110,"") -> 0.0011551791 | S110: =IFERROR(M110/MEDIAN(INDEX($M$5:$M$665,MATCH($A110-90,$A$5:$A$665,1)):INDEX($M$5:$M$665,MATCH($A110+90,$A$5:$A$665,1))),"") | T110: =IFERROR(N110/MEDIAN(INDEX($N$5:$N$665,MATCH($A110-90,$A$5:$A$665,1)):INDEX($N$5:$N$665,MATCH($A110+90,$A$5:$A$665,1))),"") | U110: =IFERROR(Q110/MEDIAN(INDEX($Q$5:$Q$665,MATCH($A110-90,$A$5:$A$665,1)):INDEX($Q$5:$Q$665,MATCH($A110+90,$A$5:$A$665,1))),"")
A111: 45037.432 | B111: 10 | C111: пт | E111: ссылка | F111: 23834 | G111: 8221 | H111: 8218 | I111: 2 | J111: 304 | K111: 17 | L111: 11 | M111: =IFERROR(G111/F111,"") -> 0.34492741 | N111: =IFERROR(H111/G111,"") -> 0.99963508 | O111: =IFERROR(I111/H111,"") -> 0.00024336822 | P111: =IFERROR(J111/H111,"") -> 0.036991969 | Q111: =IFERROR(K111/H111,"") -> 0.0020686298 | R111: =IFERROR(L111/H111,"") -> 0.0013385252 | S111: =IFERROR(M111/MEDIAN(INDEX($M$5:$M$665,MATCH($A111-90,$A$5:$A$665,1)):INDEX($M$5:$M$665,MATCH($A111+90,$A$5:$A$665,1))),"") | T111: =IFERROR(N111/MEDIAN(INDEX($N$5:$N$665,MATCH($A111-90,$A$5:$A$665,1)):INDEX($N$5:$N$665,MATCH($A111+90,$A$5:$A$665,1))),"") | U111: =IFERROR(Q111/MEDIAN(INDEX($Q$5:$Q$665,MATCH($A111-90,$A$5:$A$665,1)):INDEX($Q$5:$Q$665,MATCH($A111+90,$A$5:$A$665,1))),"")
A112: 45038.714 | B112: 17 | C112: сб | D112: В лифте #правилаэтикета #этикет #лифт #общественныеместа #этикетобщения | E112: ссылка | F112: 89025 | G112: 15087 | H112: 15082 | I112: 3 | J112: 211 | K112: 10 | L112: 11 | M112: =IFERROR(G112/F112,"") -> 0.16946925 | N112: =IFERROR(H112/G112,"") -> 0.99966859 | O112: =IFERROR(I112/H112,"") -> 0.00019891261 | P112: =IFERROR(J112/H112,"") -> 0.013990187 | Q112: =IFERROR(K112/H112,"") -> 0.00066304204 | R112: =IFERROR(L112/H112,"") -> 0.00072934624 | S112: =IFERROR(M112/MEDIAN(INDEX($M$5:$M$665,MATCH($A112-90,$A$5:$A$665,1)):INDEX($M$5:$M$665,MATCH($A112+90,$A$5:$A$665,1))),"") | T112: =IFERROR(N112/MEDIAN(INDEX($N$5:$N$665,MATCH($A112-90,$A$5:$A$665,1)):INDEX($N$5:$N$665,MATCH($A112+90,$A$5:$A$665,1))),"") | U112: =IFERROR(Q112/MEDIAN(INDEX($Q$5:$Q$665,MATCH($A112-90,$A$5:$A$665,1)):INDEX($Q$5:$Q$665,MATCH($A112+90,$A$5:$A$665,1))),"")
A113: 45039.521 | B113: 12 | C113: вс | D113: Можно не знать этикет, но.. #правилаэтикета #этикет #деловоеобщение #деловойэтикет #деловаярепутация #деловыепереговоры #этикетобщения | E113: ссылка | F113: 210821 | G113: 35177 | H113: 35171 | I113: 6 | J113: 296 | K113: 20 | L113: 24 | M113: =IFERROR(G113/F113,"") -> 0.16685719 | N113: =IFERROR(H113/G113,"") -> 0.99982943 | O113: =IFERROR(I113/H113,"") -> 0.00017059509 | P113: =IFERROR(J113/H113,"") -> 0.0084160246 | Q113: =IFERROR(K113/H113,"") -> 0.00056865031 | R113: =IFERROR(L113/H113,"") -> 0.00068238037 | S113: =IFERROR(M113/MEDIAN(INDEX($M$5:$M$665,MATCH($A113-90,$A$5:$A$665,1)):INDEX($M$5:$M$665,MATCH($A113+90,$A$5:$A$665,1))),"") | T113: =IFERROR(N113/MEDIAN(INDEX($N$5:$N$665,MATCH($A113-90,$A$5:$A$665,1)):INDEX($N$5:$N$665,MATCH($A113+90,$A$5:$A$665,1))),"") | U113: =IFERROR(Q113/MEDIAN(INDEX($Q$5:$Q$665,MATCH($A113-90,$A$5:$A$665,1)):INDEX($Q$5:$Q$665,MATCH($A113+90,$A$5:$A$665,1))),"")
A114: 45040.583 | B114: 13 | C114: пн | D114: Не дарите цветы в горшках #правилаэтикета #этикет #деловоеобщение #деловойэтикет #деловаярепутация #подарки #цветы #деловыеотношения | E114: ссылка | F114: 199781 | G114: 40291 | H114: 40292 | I114: 31 | J114: 298 | K114: 13 | L114: 15 | M114: =IFERROR(G114/F114,"") -> 0.20167583 | N114: =IFERROR(H114/G114,"") -> 1.0000248 | O114: =IFERROR(I114/H114,"") -> 0.0007693835 | P114: =IFERROR(J114/H114,"") -> 0.0073960091 | Q114: =IFERROR(K114/H114,"") -> 0.00032264469 | R114: =IFERROR(L114/H114,"") -> 0.00037228234 | S114: =IFERROR(M114/MEDIAN(INDEX($M$5:$M$665,MATCH($A114-90,$A$5:$A$665,1)):INDEX($M$5:$M$665,MATCH($A114+90,$A$5:$A$665,1))),"") | T114: =IFERROR(N114/MEDIAN(INDEX($N$5:$N$665,MATCH($A114-90,$A$5:$A$665,1)):INDEX($N$5:$N$665,MATCH($A114+90,$A$5:$A$665,1))),"") | U114: =IFERROR(Q114/MEDIAN(INDEX($Q$5:$Q$665,MATCH($A114-90,$A$5:$A$665,1)):INDEX($Q$5:$Q$665,MATCH($A114+90,$A$5:$A$665,1))),"")
A115: 45041.5 | B115: 12 | C115: вт | D115: Пишем незнакомцу #этикет #правилаэтикета #деловоеобщение #деловойэтикет #деловаярепутация #деловыепереговоры #деловаяпереписка | E115: ссылка | F115: 143201 | G115: 37279 | H115: 37276 | I115: 15 | J115: 368 | K115: 14 | L115: 43 | M115: =IFERROR(G115/F115,"") -> 0.26032639 | N115: =IFERROR(H115/G115,"") -> 0.99991953 | O115: =IFERROR(I115/H115,"") -> 0.00040240369 | P115: =IFERROR(J115/H115,"") -> 0.0098723039 | Q115: =IFERROR(K115/H115,"") -> 0.00037557678 | R115: =IFERROR(L115/H115,"") -> 0.0011535572 | S115: =IFERROR(M115/MEDIAN(INDEX($M$5:$M$665,MATCH($A115-90,$A$5:$A$665,1)):INDEX($M$5:$M$665,MATCH($A115+90,$A$5:$A$665,1))),"") | T115: =IFERROR(N115/MEDIAN(INDEX($N$5:$N$665,MATCH($A115-90,$A$5:$A$665,1)):INDEX($N$5:$N$665,MATCH($A115+90,$A$5:$A$665,1))),"") | U115: =IFERROR(Q115/MEDIAN(INDEX($Q$5:$Q$665,MATCH($A115-90,$A$5:$A$665,1)):INDEX($Q$5:$Q$665,MATCH($A115+90,$A$5:$A$665,1))),"")
A116: 45042.5 | B116: 12 | C116: ср | D116: Заботливый хозяин | E116: ссылка | F116: 156049 | G116: 24401 | H116: 24396 | I116: 2 | J116: 260 | K116: 35 | L116: 15 | M116: =IFERROR(G116/F116,"") -> 0.15636755 | N116: =IFERROR(H116/G116,"") -> 0.99979509 | O116: =IFERROR(I116/H116,"") -> 8.1980653e-05 | P116: =IFERROR(J116/H116,"") -> 0.010657485 | Q116: =IFERROR(K116/H116,"") -> 0.0014346614 | R116: =IFERROR(L116/H116,"") -> 0.00061485489 | S116: =IFERROR(M116/MEDIAN(INDEX($M$5:$M$665,MATCH($A116-90,$A$5:$A$665,1)):INDEX($M$5:$M$665,MATCH($A116+90,$A$5:$A$665,1))),"") | T116: =IFERROR(N116/MEDIAN(INDEX($N$5:$N$665,MATCH($A116-90,$A$5:$A$665,1)):INDEX($N$5:$N$665,MATCH($A116+90,$A$5:$A$665,1))),"") | U116: =IFERROR(Q116/MEDIAN(INDEX($Q$5:$Q$665,MATCH($A116-90,$A$5:$A$665,1)):INDEX($Q$5:$Q$665,MATCH($A116+90,$A$5:$A$665,1))),"")
A117: 45043.479 | B117: 11 | C117: чт | D117: Проверьте ваши знания #этикет #правилаэтикета #этикетобщения #деловойэтикет #деловаярепутация #деловойимидж #деловыепереговоры #деловоеобщение #деловыеотношения | E117: ссылка | F117: 6309 | G117: 3059 | H117: 3067 | I117: 25 | J117: 214 | K117: 20 | L117: 11 | M117: =IFERROR(G117/F117,"") -> 0.48486289 | N117: =IFERROR(H117/G117,"") -> 1.0026152 | O117: =IFERROR(I117/H117,"") -> 0.0081512879 | P117: =IFERROR(J117/H117,"") -> 0.069775024 | Q117: =IFERROR(K117/H117,"") -> 0.0065210303 | R117: =IFERROR(L117/H117,"") -> 0.0035865667 | S117: =IFERROR(M117/MEDIAN(INDEX($M$5:$M$665,MATCH($A117-90,$A$5:$A$665,1)):INDEX($M$5:$M$665,MATCH($A117+90,$A$5:$A$665,1))),"") | T117: =IFERROR(N117/MEDIAN(INDEX($N$5:$N$665,MATCH($A117-90,$A$5:$A$665,1)):INDEX($N$5:$N$665,MATCH($A117+90,$A$5:$A$665,1))),"") | U117: =IFERROR(Q117/MEDIAN(INDEX($Q$5:$Q$665,MATCH($A117-90,$A$5:$A$665,1)):INDEX($Q$5:$Q$665,MATCH($A117+90,$A$5:$A$665,1))),"")
A118: 45044.512 | B118: 12 | C118: пт | D118: Комплимент или скандал? #этикет #правилаэтикета #этикетобщения #деловаярепутация #деловойэтикет #комплимент #комплименты #деловоеобщение #деловыеотношения | E118: ссылка | F118: 306072 | G118: 37373 | H118: 37381 | I118: 32 | J118: 343 | K118: 19 | L118: 24 | M118: =IFERROR(G118/F118,"") -> 0.12210526 | N118: =IFERROR(H118/G118,"") -> 1.0002141 | O118: =IFERROR(I118/H118,"") -> 0.00085604986 | P118: =IFERROR(J118/H118,"") -> 0.0091757845 | Q118: =IFERROR(K118/H118,"") -> 0.00050827961 | R118: =IFERROR(L118/H118,"") -> 0.0006420374 | S118: =IFERROR(M118/MEDIAN(INDEX($M$5:$M$665,MATCH($A118-90,$A$5:$A$665,1)):INDEX($M$5:$M$665,MATCH($A118+90,$A$5:$A$665,1))),"") | T118: =IFERROR(N118/MEDIAN(INDEX($N$5:$N$665,MATCH($A118-90,$A$5:$A$665,1)):INDEX($N$5:$N$665,MATCH($A118+90,$A$5:$A$665,1))),"") | U118: =IFERROR(Q118/MEDIAN(INDEX($Q$5:$Q$665,MATCH($A118-90,$A$5:$A$665,1)):INDEX($Q$5:$Q$665,MATCH($A118+90,$A$5:$A$665,1))),"")
A119: 45045.518 | B119: 12 | C119: сб | D119: Вещь взаймы | E119: ссылка | F119: 34297 | G119: 11225 | H119: 11223 | I119: 2 | J119: 317 | K119: 40 | L119: 7 | M119: =IFERROR(G119/F119,"") -> 0.3272881 | N119: =IFERROR(H119/G119,"") -> 0.99982183 | O119: =IFERROR(I119/H119,"") -> 0.00017820547 | P119: =IFERROR(J119/H119,"") -> 0.028245567 | Q119: =IFERROR(K119/H119,"") -> 0.0035641094 | R119: =IFERROR(L119/H119,"") -> 0.00062371915 | S119: =IFERROR(M119/MEDIAN(INDEX($M$5:$M$665,MATCH($A119-90,$A$5:$A$665,1)):INDEX($M$5:$M$665,MATCH($A119+90,$A$5:$A$665,1))),"") | T119: =IFERROR(N119/MEDIAN(INDEX($N$5:$N$665,MATCH($A119-90,$A$5:$A$665,1)):INDEX($N$5:$N$665,MATCH($A119+90,$A$5:$A$665,1))),"") | U119: =IFERROR(Q119/MEDIAN(INDEX($Q$5:$Q$665,MATCH($A119-90,$A$5:$A$665,1)):INDEX($Q$5:$Q$665,MATCH($A119+90,$A$5:$A$665,1))),"")
A120: 45046.586 | B120: 14 | C120: вс | D120: Этикет на даче | E120: ссылка | F120: 446231 | G120: 55146 | H120: 55140 | I120: 3 | J120: 286 | K120: 22 | L120: 14 | M120: =IFERROR(G120/F120,"") -> 0.12358173 | N120: =IFERROR(H120/G120,"") -> 0.9998912 | O120: =IFERROR(I120/H120,"") -> 5.4406964e-05 | P120: =IFERROR(J120/H120,"") -> 0.0051867972 | Q120: =IFERROR(K120/H120,"") -> 0.0003989844 | R120: =IFERROR(L120/H120,"") -> 0.00025389917 | S120: =IFERROR(M120/MEDIAN(INDEX($M$5:$M$665,MATCH($A120-90,$A$5:$A$665,1)):INDEX($M$5:$M$665,MATCH($A120+90,$A$5:$A$665,1))),"") | T120: =IFERROR(N120/MEDIAN(INDEX($N$5:$N$665,MATCH($A120-90,$A$5:$A$665,1)):INDEX($N$5:$N$665,MATCH($A120+90,$A$5:$A$665,1))),"") | U120: =IFERROR(Q120/MEDIAN(INDEX($Q$5:$Q$665,MATCH($A120-90,$A$5:$A$665,1)):INDEX($Q$5:$Q$665,MATCH($A120+90,$A$5:$A$665,1))),"")
A121: 45047.883 | B121: 21 | C121: пн | E121: ссылка | F121: 16921 | G121: 7134 | H121: 7130 | I121: 0 | J121: 221 | K121: 8 | L121: 3 | M121: =IFERROR(G121/F121,"") -> 0.42160629 | N121: =IFERROR(H121/G121,"") -> 0.9994393 | O121: =IFERROR(I121/H121,"") -> 0 | P121: =IFERROR(J121/H121,"") -> 0.030995792 | Q121: =IFERROR(K121/H121,"") -> 0.0011220196 | R121: =IFERROR(L121/H121,"") -> 0.00042075736 | S121: =IFERROR(M121/MEDIAN(INDEX($M$5:$M$665,MATCH($A121-90,$A$5:$A$665,1)):INDEX($M$5:$M$665,MATCH($A121+90,$A$5:$A$665,1))),"") | T121: =IFERROR(N121/MEDIAN(INDEX($N$5:$N$665,MATCH($A121-90,$A$5:$A$665,1)):INDEX($N$5:$N$665,MATCH($A121+90,$A$5:$A$665,1))),"") | U121: =IFERROR(Q121/MEDIAN(INDEX($Q$5:$Q$665,MATCH($A121-90,$A$5:$A$665,1)):INDEX($Q$5:$Q$665,MATCH($A121+90,$A$5:$A$665,1))),"")
A122: 45048.606 | B122: 14 | C122: вт | E122: ссылка | F122: 163355 | G122: 23922 | H122: 23919 | I122: 1 | J122: 278 | K122: 25 | L122: 11 | M122: =IFERROR(G122/F122,"") -> 0.1464418 | N122: =IFERROR(H122/G122,"") -> 0.99987459 | O122: =IFERROR(I122/H122,"") -> 4.1807768e-05 | P122: =IFERROR(J122/H122,"") -> 0.011622559 | Q122: =IFERROR(K122/H122,"") -> 0.0010451942 | R122: =IFERROR(L122/H122,"") -> 0.00045988545 | S122: =IFERROR(M122/MEDIAN(INDEX($M$5:$M$665,MATCH($A122-90,$A$5:$A$665,1)):INDEX($M$5:$M$665,MATCH($A122+90,$A$5:$A$665,1))),"") | T122: =IFERROR(N122/MEDIAN(INDEX($N$5:$N$665,MATCH($A122-90,$A$5:$A$665,1)):INDEX($N$5:$N$665,MATCH($A122+90,$A$5:$A$665,1))),"") | U122: =IFERROR(Q122/MEDIAN(INDEX($Q$5:$Q$665,MATCH($A122-90,$A$5:$A$665,1)):INDEX($Q$5:$Q$665,MATCH($A122+90,$A$5:$A$665,1))),"")
A123: 45049.818 | B123: 19 | C123: ср | E123: ссылка | F123: 100142 | G123: 27128 | H123: 27129 | I123: 3 | J123: 382 | K123: 13 | L123: 28 | M123: =IFERROR(G123/F123,"") -> 0.27089533 | N123: =IFERROR(H123/G123,"") -> 1.0000369 | O123: =IFERROR(I123/H123,"") -> 0.00011058277 | P123: =IFERROR(J123/H123,"") -> 0.014080873 | Q123: =IFERROR(K123/H123,"") -> 0.00047919201 | R123: =IFERROR(L123/H123,"") -> 0.0010321059 | S123: =IFERROR(M123/MEDIAN(INDEX($M$5:$M$665,MATCH($A123-90,$A$5:$A$665,1)):INDEX($M$5:$M$665,MATCH($A123+90,$A$5:$A$665,1))),"") | T123: =IFERROR(N123/MEDIAN(INDEX($N$5:$N$665,MATCH($A123-90,$A$5:$A$665,1)):INDEX($N$5:$N$665,MATCH($A123+90,$A$5:$A$665,1))),"") | U123: =IFERROR(Q123/MEDIAN(INDEX($Q$5:$Q$665,MATCH($A123-90,$A$5:$A$665,1)):INDEX($Q$5:$Q$665,MATCH($A123+90,$A$5:$A$665,1))),"")
A124: 45050.891 | B124: 21 | C124: чт | D124: Проверьте ваши знания 😌 | E124: ссылка | F124: 5249 | G124: 2061 | H124: 2068 | I124: 25 | J124: 142 | K124: 14 | L124: 5 | M124: =IFERROR(G124/F124,"") -> 0.39264622 | N124: =IFERROR(H124/G124,"") -> 1.0033964 | O124: =IFERROR(I124/H124,"") -> 0.012088975 | P124: =IFERROR(J124/H124,"") -> 0.068665377 | Q124: =IFERROR(K124/H124,"") -> 0.0067698259 | R124: =IFERROR(L124/H124,"") -> 0.002417795 | S124: =IFERROR(M124/MEDIAN(INDEX($M$5:$M$665,MATCH($A124-90,$A$5:$A$665,1)):INDEX($M$5:$M$665,MATCH($A124+90,$A$5:$A$665,1))),"") -> 0.98368646 | T124: =IFERROR(N124/MEDIAN(INDEX($N$5:$N$665,MATCH($A124-90,$A$5:$A$665,1)):INDEX($N$5:$N$665,MATCH($A124+90,$A$5:$A$665,1))),"") -> 1.0035503 | U124: =IFERROR(Q124/MEDIAN(INDEX($Q$5:$Q$665,MATCH($A124-90,$A$5:$A$665,1)):INDEX($Q$5:$Q$665,MATCH($A124+90,$A$5:$A$665,1))),"") -> 5.5508732
A125: 45051.584 | B125: 14 | C125: пт | D125: В поезде дальнего следования | E125: ссылка | F125: 362102 | G125: 58072 | H125: 58068 | I125: 2 | J125: 333 | K125: 27 | L125: 34 | M125: =IFERROR(G125/F125,"") -> 0.1603747 | N125: =IFERROR(H125/G125,"") -> 0.99993112 | O125: =IFERROR(I125/H125,"") -> 3.4442378e-05 | P125: =IFERROR(J125/H125,"") -> 0.0057346559 | Q125: =IFERROR(K125/H125,"") -> 0.0004649721 | R125: =IFERROR(L125/H125,"") -> 0.00058552042 | S125: =IFERROR(M125/MEDIAN(INDEX($M$5:$M$665,MATCH($A125-90,$A$5:$A$665,1)):INDEX($M$5:$M$665,MATCH($A125+90,$A$5:$A$665,1))),"") -> 0.40322815 | T125: =IFERROR(N125/MEDIAN(INDEX($N$5:$N$665,MATCH($A125-90,$A$5:$A$665,1)):INDEX($N$5:$N$665,MATCH($A125+90,$A$5:$A$665,1))),"") -> 1.0000846 | U125: =IFERROR(Q125/MEDIAN(INDEX($Q$5:$Q$665,MATCH($A125-90,$A$5:$A$665,1)):INDEX($Q$5:$Q$665,MATCH($A125+90,$A$5:$A$665,1))),"") -> 0.38016119
A126: 45052.912 | B126: 21 | C126: сб | D126: Шведский стол | E126: ссылка | F126: 27768 | G126: 14833 | H126: 14833 | I126: 43 | J126: 347 | K126: 16 | L126: 17 | M126: =IFERROR(G126/F126,"") -> 0.53417603 | N126: =IFERROR(H126/G126,"") -> 1 | O126: =IFERROR(I126/H126,"") -> 0.0028989415 | P126: =IFERROR(J126/H126,"") -> 0.023393784 | Q126: =IFERROR(K126/H126,"") -> 0.0010786759 | R126: =IFERROR(L126/H126,"") -> 0.0011460932 | S126: =IFERROR(M126/MEDIAN(INDEX($M$5:$M$665,MATCH($A126-90,$A$5:$A$665,1)):INDEX($M$5:$M$665,MATCH($A126+90,$A$5:$A$665,1))),"") -> 1.3627799 | T126: =IFERROR(N126/MEDIAN(INDEX($N$5:$N$665,MATCH($A126-90,$A$5:$A$665,1)):INDEX($N$5:$N$665,MATCH($A126+90,$A$5:$A$665,1))),"") -> 1.0001601 | U126: =IFERROR(Q126/MEDIAN(INDEX($Q$5:$Q$665,MATCH($A126-90,$A$5:$A$665,1)):INDEX($Q$5:$Q$665,MATCH($A126+90,$A$5:$A$665,1))),"") -> 0.89764806
A127: 45053.5 | B127: 12 | C127: вс | D127: Дворовый этикет | E127: ссылка | F127: 135385 | G127: 19573 | H127: 19570 | I127: 1 | J127: 185 | K127: 12 | L127: 13 | M127: =IFERROR(G127/F127,"") -> 0.14457288 | N127: =IFERROR(H127/G127,"") -> 0.99984673 | O127: =IFERROR(I127/H127,"") -> 5.109862e-05 | P127: =IFERROR(J127/H127,"") -> 0.0094532448 | Q127: =IFERROR(K127/H127,"") -> 0.00061318344 | R127: =IFERROR(L127/H127,"") -> 0.00066428206 | S127: =IFERROR(M127/MEDIAN(INDEX($M$5:$M$665,MATCH($A127-90,$A$5:$A$665,1)):INDEX($M$5:$M$665,MATCH($A127+90,$A$5:$A$665,1))),"") -> 0.36820139 | T127: =IFERROR(N127/MEDIAN(INDEX($N$5:$N$665,MATCH($A127-90,$A$5:$A$665,1)):INDEX($N$5:$N$665,MATCH($A127+90,$A$5:$A$665,1))),"") -> 1.0000062 | U127: =IFERROR(Q127/MEDIAN(INDEX($Q$5:$Q$665,MATCH($A127-90,$A$5:$A$665,1)):INDEX($Q$5:$Q$665,MATCH($A127+90,$A$5:$A$665,1))),"") -> 0.50965764
A128: 45054.525 | B128: 12 | C128: пн | D128: Комментарии #этикет #правилаэтикета | E128: ссылка | F128: 83080 | G128: 21041 | H128: 21042 | I128: 16 | J128: 328 | K128: 49 | L128: 21 | M128: =IFERROR(G128/F128,"") -> 0.25326192 | N128: =IFERROR(H128/G128,"") -> 1.0000475 | O128: =IFERROR(I128/H128,"") -> 0.00076038399 | P128: =IFERROR(J128/H128,"") -> 0.015587872 | Q128: =IFERROR(K128/H128,"") -> 0.002328676 | R128: =IFERROR(L128/H128,"") -> 0.00099800399 | S128: =IFERROR(M128/MEDIAN(INDEX($M$5:$M$665,MATCH($A128-90,$A$5:$A$665,1)):INDEX($M$5:$M$665,MATCH($A128+90,$A$5:$A$665,1))),"") -> 0.64086669 | T128: =IFERROR(N128/MEDIAN(INDEX($N$5:$N$665,MATCH($A128-90,$A$5:$A$665,1)):INDEX($N$5:$N$665,MATCH($A128+90,$A$5:$A$665,1))),"") -> 1.0002076 | U128: =IFERROR(Q128/MEDIAN(INDEX($Q$5:$Q$665,MATCH($A128-90,$A$5:$A$665,1)):INDEX($Q$5:$Q$665,MATCH($A128+90,$A$5:$A$665,1))),"") -> 1.9251387
A129: 45056.58 | B129: 13 | C129: ср | D129: Шумная компания | E129: ссылка | F129: 70812 | G129: 11527 | H129: 11522 | I129: 1 | J129: 225 | K129: 19 | L129: 14 | M129: =IFERROR(G129/F129,"") -> 0.16278314 | N129: =IFERROR(H129/G129,"") -> 0.99956624 | O129: =IFERROR(I129/H129,"") -> 8.6790488e-05 | P129: =IFERROR(J129/H129,"") -> 0.01952786 | Q129: =IFERROR(K129/H129,"") -> 0.0016490193 | R129: =IFERROR(L129/H129,"") -> 0.0012150668 | S129: =IFERROR(M129/MEDIAN(INDEX($M$5:$M$665,MATCH($A129-90,$A$5:$A$665,1)):INDEX($M$5:$M$665,MATCH($A129+90,$A$5:$A$665,1))),"") -> 0.41766387 | T129: =IFERROR(N129/MEDIAN(INDEX($N$5:$N$665,MATCH($A129-90,$A$5:$A$665,1)):INDEX($N$5:$N$665,MATCH($A129+90,$A$5:$A$665,1))),"") -> 0.99972623 | U129: =IFERROR(Q129/MEDIAN(INDEX($Q$5:$Q$665,MATCH($A129-90,$A$5:$A$665,1)):INDEX($Q$5:$Q$665,MATCH($A129+90,$A$5:$A$665,1))),"") -> 1.375255
A130: 45057.585 | B130: 14 | C130: чт | D130: Головной убор в ресторане | E130: ссылка | F130: 46658 | G130: 12314 | H130: 12310 | I130: 56 | J130: 242 | K130: 21 | L130: 9 | M130: =IFERROR(G130/F130,"") -> 0.26392044 | N130: =IFERROR(H130/G130,"") -> 0.99967517 | O130: =IFERROR(I130/H130,"") -> 0.004549147 | P130: =IFERROR(J130/H130,"") -> 0.019658814 | Q130: =IFERROR(K130/H130,"") -> 0.0017059301 | R130: =IFERROR(L130/H130,"") -> 0.00073111292 | S130: =IFERROR(M130/MEDIAN(INDEX($M$5:$M$665,MATCH($A130-90,$A$5:$A$665,1)):INDEX($M$5:$M$665,MATCH($A130+90,$A$5:$A$665,1))),"") -> 0.6831266 | T130: =IFERROR(N130/MEDIAN(INDEX($N$5:$N$665,MATCH($A130-90,$A$5:$A$665,1)):INDEX($N$5:$N$665,MATCH($A130+90,$A$5:$A$665,1))),"") -> 0.99983603 | U130: =IFERROR(Q130/MEDIAN(INDEX($Q$5:$Q$665,MATCH($A130-90,$A$5:$A$665,1)):INDEX($Q$5:$Q$665,MATCH($A130+90,$A$5:$A$665,1))),"") -> 1.4227178
A131: 45058.573 | B131: 13 | C131: пт | D131: Время проверить свои знания 🙌🏻 | E131: ссылка | F131: 6284 | G131: 2595 | H131: 2601 | I131: 32 | J131: 182 | K131: 12 | L131: 2 | M131: =IFERROR(G131/F131,"") -> 0.41295353 | N131: =IFERROR(H131/G131,"") -> 1.0023121 | O131: =IFERROR(I131/H131,"") -> 0.01230296 | P131: =IFERROR(J131/H131,"") -> 0.069973087 | Q131: =IFERROR(K131/H131,"") -> 0.0046136102 | R131: =IFERROR(L131/H131,"") -> 0.00076893503 | S131: =IFERROR(M131/MEDIAN(INDEX($M$5:$M$665,MATCH($A131-90,$A$5:$A$665,1)):INDEX($M$5:$M$665,MATCH($A131+90,$A$5:$A$665,1))),"") -> 1.068881 | T131: =IFERROR(N131/MEDIAN(INDEX($N$5:$N$665,MATCH($A131-90,$A$5:$A$665,1)):INDEX($N$5:$N$665,MATCH($A131+90,$A$5:$A$665,1))),"") -> 1.0024726 | U131: =IFERROR(Q131/MEDIAN(INDEX($Q$5:$Q$665,MATCH($A131-90,$A$5:$A$665,1)):INDEX($Q$5:$Q$665,MATCH($A131+90,$A$5:$A$665,1))),"") -> 3.8031258
A132: 45059.552 | B132: 13 | C132: сб | D132: Пляжный отдых | E132: ссылка | F132: 126220 | G132: 26221 | H132: 26216 | I132: 7 | J132: 323 | K132: 18 | L132: 36 | M132: =IFERROR(G132/F132,"") -> 0.20774045 | N132: =IFERROR(H132/G132,"") -> 0.99980931 | O132: =IFERROR(I132/H132,"") -> 0.00026701251 | P132: =IFERROR(J132/H132,"") -> 0.01232072 | Q132: =IFERROR(K132/H132,"") -> 0.0006866036 | R132: =IFERROR(L132/H132,"") -> 0.0013732072 | S132: =IFERROR(M132/MEDIAN(INDEX($M$5:$M$665,MATCH($A132-90,$A$5:$A$665,1)):INDEX($M$5:$M$665,MATCH($A132+90,$A$5:$A$665,1))),"") -> 0.54087354 | T132: =IFERROR(N132/MEDIAN(INDEX($N$5:$N$665,MATCH($A132-90,$A$5:$A$665,1)):INDEX($N$5:$N$665,MATCH($A132+90,$A$5:$A$665,1))),"") -> 0.99996279 | U132: =IFERROR(Q132/MEDIAN(INDEX($Q$5:$Q$665,MATCH($A132-90,$A$5:$A$665,1)):INDEX($Q$5:$Q$665,MATCH($A132+90,$A$5:$A$665,1))),"") -> 0.5613671
A133: 45060.501 | B133: 12 | C133: вс | D133: Место в поезде | E133: ссылка | F133: 14707 | G133: 6310 | H133: 6303 | I133: 12 | J133: 264 | K133: 11 | L133: 4 | M133: =IFERROR(G133/F133,"") -> 0.42904739 | N133: =IFERROR(H133/G133,"") -> 0.99889065 | O133: =IFERROR(I133/H133,"") -> 0.0019038553 | P133: =IFERROR(J133/H133,"") -> 0.041884817 | Q133: =IFERROR(K133/H133,"") -> 0.0017452007 | R133: =IFERROR(L133/H133,"") -> 0.00063461844 | S133: =IFERROR(M133/MEDIAN(INDEX($M$5:$M$665,MATCH($A133-90,$A$5:$A$665,1)):INDEX($M$5:$M$665,MATCH($A133+90,$A$5:$A$665,1))),"") -> 1.1286182 | T133: =IFERROR(N133/MEDIAN(INDEX($N$5:$N$665,MATCH($A133-90,$A$5:$A$665,1)):INDEX($N$5:$N$665,MATCH($A133+90,$A$5:$A$665,1))),"") -> 0.99904998 | U133: =IFERROR(Q133/MEDIAN(INDEX($Q$5:$Q$665,MATCH($A133-90,$A$5:$A$665,1)):INDEX($Q$5:$Q$665,MATCH($A133+90,$A$5:$A$665,1))),"") -> 1.4268761
A134: 45061.5 | B134: 12 | C134: пн | D134: Жилой двор | E134: ссылка | F134: 48095 | G134: 14153 | H134: 14149 | I134: 1 | J134: 243 | K134: 20 | L134: 12 | M134: =IFERROR(G134/F134,"") -> 0.29427175 | N134: =IFERROR(H134/G134,"") -> 0.99971737 | O134: =IFERROR(I134/H134,"") -> 7.0676373e-05 | P134: =IFERROR(J134/H134,"") -> 0.017174359 | Q134: =IFERROR(K134/H134,"") -> 0.0014135275 | R134: =IFERROR(L134/H134,"") -> 0.00084811647 | S134: =IFERROR(M134/MEDIAN(INDEX($M$5:$M$665,MATCH($A134-90,$A$5:$A$665,1)):INDEX($M$5:$M$665,MATCH($A134+90,$A$5:$A$665,1))),"") -> 0.77457183 | T134: =IFERROR(N134/MEDIAN(INDEX($N$5:$N$665,MATCH($A134-90,$A$5:$A$665,1)):INDEX($N$5:$N$665,MATCH($A134+90,$A$5:$A$665,1))),"") -> 0.9998774 | U134: =IFERROR(Q134/MEDIAN(INDEX($Q$5:$Q$665,MATCH($A134-90,$A$5:$A$665,1)):INDEX($Q$5:$Q$665,MATCH($A134+90,$A$5:$A$665,1))),"") -> 1.1531065
A135: 45062.498 | B135: 11 | C135: вт | D135: Цените людей | E135: ссылка | F135: 58171 | G135: 11846 | H135: 11842 | I135: 1 | J135: 354 | K135: 19 | L135: 20 | M135: =IFERROR(G135/F135,"") -> 0.20364099 | N135: =IFERROR(H135/G135,"") -> 0.99966233 | O135: =IFERROR(I135/H135,"") -> 8.4445195e-05 | P135: =IFERROR(J135/H135,"") -> 0.029893599 | Q135: =IFERROR(K135/H135,"") -> 0.0016044587 | R135: =IFERROR(L135/H135,"") -> 0.0016889039 | S135: =IFERROR(M135/MEDIAN(INDEX($M$5:$M$665,MATCH($A135-90,$A$5:$A$665,1)):INDEX($M$5:$M$665,MATCH($A135+90,$A$5:$A$665,1))),"") -> 0.5405331 | T135: =IFERROR(N135/MEDIAN(INDEX($N$5:$N$665,MATCH($A135-90,$A$5:$A$665,1)):INDEX($N$5:$N$665,MATCH($A135+90,$A$5:$A$665,1))),"") -> 0.99982235 | U135: =IFERROR(Q135/MEDIAN(INDEX($Q$5:$Q$665,MATCH($A135-90,$A$5:$A$665,1)):INDEX($Q$5:$Q$665,MATCH($A135+90,$A$5:$A$665,1))),"") -> 1.310711
... A236: 45162.675 | B236: 16 | C236: чт | D236: Вести параллельно два диалога - не лучший вариант | E236: ссылка | F236: 6238 | G236: 3622 | H236: 3617 | I236: 822 | J236: 235 | K236: 5 | L236: 0 | M236: =IFERROR(G236/F236,"") -> 0.58063482 | N236: =IFERROR(H236/G236,"") -> 0.99861955 | O236: =IFERROR(I236/H236,"") -> 0.22726016 | P236: =IFERROR(J236/H236,"") -> 0.06497097 | Q236: =IFERROR(K236/H236,"") -> 0.0013823611 | R236: =IFERROR(L236/H236,"") -> 0 | S236: =IFERROR(M236/MEDIAN(INDEX($M$5:$M$665,MATCH($A236-90,$A$5:$A$665,1)):INDEX($M$5:$M$665,MATCH($A236+90,$A$5:$A$665,1))),"") -> 1.350966 | T236: =IFERROR(N236/MEDIAN(INDEX($N$5:$N$665,MATCH($A236-90,$A$5:$A$665,1)):INDEX($N$5:$N$665,MATCH($A236+90,$A$5:$A$665,1))),"") -> 0.99897615 | U236: =IFERROR(Q236/MEDIAN(INDEX($Q$5:$Q$665,MATCH($A236-90,$A$5:$A$665,1)):INDEX($Q$5:$Q$665,MATCH($A236+90,$A$5:$A$665,1))),"") -> 1.3203565
A237: 45163.773 | B237: 18 | C237: пт | E237: ссылка | F237: 55675 | G237: 22838 | H237: 22834 | I237: 3326 | J237: 341 | K237: 18 | L237: 25 | M237: =IFERROR(G237/F237,"") -> 0.41020207 | N237: =IFERROR(H237/G237,"") -> 0.99982485 | O237: =IFERROR(I237/H237,"") -> 0.14565998 | P237: =IFERROR(J237/H237,"") -> 0.014933871 | Q237: =IFERROR(K237/H237,"") -> 0.00078829815 | R237: =IFERROR(L237/H237,"") -> 0.0010948585 | S237: =IFERROR(M237/MEDIAN(INDEX($M$5:$M$665,MATCH($A237-90,$A$5:$A$665,1)):INDEX($M$5:$M$665,MATCH($A237+90,$A$5:$A$665,1))),"") -> 0.95441925 | T237: =IFERROR(N237/MEDIAN(INDEX($N$5:$N$665,MATCH($A237-90,$A$5:$A$665,1)):INDEX($N$5:$N$665,MATCH($A237+90,$A$5:$A$665,1))),"") -> 1.0001819 | U237: =IFERROR(Q237/MEDIAN(INDEX($Q$5:$Q$665,MATCH($A237-90,$A$5:$A$665,1)):INDEX($Q$5:$Q$665,MATCH($A237+90,$A$5:$A$665,1))),"") -> 0.7477976
A238: 45164.748 | B238: 17 | C238: сб | D238: Конфуз в ресторане | E238: ссылка | F238: 8367 | G238: 4749 | H238: 4743 | I238: 1288 | J238: 294 | K238: 4 | L238: 9 | M238: =IFERROR(G238/F238,"") -> 0.56758695 | N238: =IFERROR(H238/G238,"") -> 0.99873658 | O238: =IFERROR(I238/H238,"") -> 0.27155809 | P238: =IFERROR(J238/H238,"") -> 0.061986085 | Q238: =IFERROR(K238/H238,"") -> 0.00084334809 | R238: =IFERROR(L238/H238,"") -> 0.0018975332 | S238: =IFERROR(M238/MEDIAN(INDEX($M$5:$M$665,MATCH($A238-90,$A$5:$A$665,1)):INDEX($M$5:$M$665,MATCH($A238+90,$A$5:$A$665,1))),"") -> 1.3215042 | T238: =IFERROR(N238/MEDIAN(INDEX($N$5:$N$665,MATCH($A238-90,$A$5:$A$665,1)):INDEX($N$5:$N$665,MATCH($A238+90,$A$5:$A$665,1))),"") -> 0.99909203 | U238: =IFERROR(Q238/MEDIAN(INDEX($Q$5:$Q$665,MATCH($A238-90,$A$5:$A$665,1)):INDEX($Q$5:$Q$665,MATCH($A238+90,$A$5:$A$665,1))),"") -> 0.80005622
A239: 45165.794 | B239: 19 | C239: вс | E239: ссылка | F239: 46418 | G239: 11030 | H239: 11027 | I239: 1235 | J239: 274 | K239: 11 | L239: 9 | M239: =IFERROR(G239/F239,"") -> 0.23762334 | N239: =IFERROR(H239/G239,"") -> 0.99972801 | O239: =IFERROR(I239/H239,"") -> 0.11199782 | P239: =IFERROR(J239/H239,"") -> 0.0248481 | Q239: =IFERROR(K239/H239,"") -> 0.00099755146 | R239: =IFERROR(L239/H239,"") -> 0.00081617847 | S239: =IFERROR(M239/MEDIAN(INDEX($M$5:$M$665,MATCH($A239-90,$A$5:$A$665,1)):INDEX($M$5:$M$665,MATCH($A239+90,$A$5:$A$665,1))),"") -> 0.55705676 | T239: =IFERROR(N239/MEDIAN(INDEX($N$5:$N$665,MATCH($A239-90,$A$5:$A$665,1)):INDEX($N$5:$N$665,MATCH($A239+90,$A$5:$A$665,1))),"") -> 1.0000772 | U239: =IFERROR(Q239/MEDIAN(INDEX($Q$5:$Q$665,MATCH($A239-90,$A$5:$A$665,1)):INDEX($Q$5:$Q$665,MATCH($A239+90,$A$5:$A$665,1))),"") -> 0.94634382
A240: 45166.781 | B240: 18 | C240: пн | D240: Как отказать по этикету? | E240: ссылка | F240: 34379 | G240: 10572 | H240: 10573 | I240: 2261 | J240: 472 | K240: 19 | L240: 17 | M240: =IFERROR(G240/F240,"") -> 0.30751331 | N240: =IFERROR(H240/G240,"") -> 1.0000946 | O240: =IFERROR(I240/H240,"") -> 0.21384659 | P240: =IFERROR(J240/H240,"") -> 0.044642013 | Q240: =IFERROR(K240/H240,"") -> 0.0017970302 | R240: =IFERROR(L240/H240,"") -> 0.0016078691 | S240: =IFERROR(M240/MEDIAN(INDEX($M$5:$M$665,MATCH($A240-90,$A$5:$A$665,1)):INDEX($M$5:$M$665,MATCH($A240+90,$A$5:$A$665,1))),"") -> 0.72089875 | T240: =IFERROR(N240/MEDIAN(INDEX($N$5:$N$665,MATCH($A240-90,$A$5:$A$665,1)):INDEX($N$5:$N$665,MATCH($A240+90,$A$5:$A$665,1))),"") -> 1.0004439 | U240: =IFERROR(Q240/MEDIAN(INDEX($Q$5:$Q$665,MATCH($A240-90,$A$5:$A$665,1)):INDEX($Q$5:$Q$665,MATCH($A240+90,$A$5:$A$665,1))),"") -> 1.7282296
A241: 45167.706 | B241: 16 | C241: вт | D241: Разговоры по телефону в общественных местах | E241: ссылка | F241: 7490 | G241: 4284 | H241: 4282 | I241: 676 | J241: 224 | K241: 1 | L241: 1 | M241: =IFERROR(G241/F241,"") -> 0.57196262 | N241: =IFERROR(H241/G241,"") -> 0.99953315 | O241: =IFERROR(I241/H241,"") -> 0.15787015 | P241: =IFERROR(J241/H241,"") -> 0.052312004 | Q241: =IFERROR(K241/H241,"") -> 0.00023353573 | R241: =IFERROR(L241/H241,"") -> 0.00023353573 | S241: =IFERROR(M241/MEDIAN(INDEX($M$5:$M$665,MATCH($A241-90,$A$5:$A$665,1)):INDEX($M$5:$M$665,MATCH($A241+90,$A$5:$A$665,1))),"") -> 1.336252 | T241: =IFERROR(N241/MEDIAN(INDEX($N$5:$N$665,MATCH($A241-90,$A$5:$A$665,1)):INDEX($N$5:$N$665,MATCH($A241+90,$A$5:$A$665,1))),"") -> 0.99988089 | U241: =IFERROR(Q241/MEDIAN(INDEX($Q$5:$Q$665,MATCH($A241-90,$A$5:$A$665,1)):INDEX($Q$5:$Q$665,MATCH($A241+90,$A$5:$A$665,1))),"") -> 0.22604318
A242: 45168.651 | B242: 15 | C242: ср | D242: Семейные наименования | E242: ссылка | F242: 22428 | G242: 9367 | H242: 9360 | I242: 2387 | J242: 270 | K242: 10 | L242: 9 | M242: =IFERROR(G242/F242,"") -> 0.41764758 | N242: =IFERROR(H242/G242,"") -> 0.9992527 | O242: =IFERROR(I242/H242,"") -> 0.25502137 | P242: =IFERROR(J242/H242,"") -> 0.028846154 | Q242: =IFERROR(K242/H242,"") -> 0.0010683761 | R242: =IFERROR(L242/H242,"") -> 0.00096153846 | S242: =IFERROR(M242/MEDIAN(INDEX($M$5:$M$665,MATCH($A242-90,$A$5:$A$665,1)):INDEX($M$5:$M$665,MATCH($A242+90,$A$5:$A$665,1))),"") -> 0.97573231 | T242: =IFERROR(N242/MEDIAN(INDEX($N$5:$N$665,MATCH($A242-90,$A$5:$A$665,1)):INDEX($N$5:$N$665,MATCH($A242+90,$A$5:$A$665,1))),"") -> 0.99960503 | U242: =IFERROR(Q242/MEDIAN(INDEX($Q$5:$Q$665,MATCH($A242-90,$A$5:$A$665,1)):INDEX($Q$5:$Q$665,MATCH($A242+90,$A$5:$A$665,1))),"") -> 1.0340992
A243: 45169.697 | B243: 16 | C243: чт | D243: Китайское метро | E243: ссылка | F243: 98756 | G243: 32787 | H243: 32771 | I243: 5534 | J243: 379 | K243: 8 | L243: 6 | M243: =IFERROR(G243/F243,"") -> 0.33200008 | N243: =IFERROR(H243/G243,"") -> 0.999512 | O243: =IFERROR(I243/H243,"") -> 0.16886882 | P243: =IFERROR(J243/H243,"") -> 0.011565103 | Q243: =IFERROR(K243/H243,"") -> 0.00024411828 | R243: =IFERROR(L243/H243,"") -> 0.00018308871 | S243: =IFERROR(M243/MEDIAN(INDEX($M$5:$M$665,MATCH($A243-90,$A$5:$A$665,1)):INDEX($M$5:$M$665,MATCH($A243+90,$A$5:$A$665,1))),"") -> 0.77299083 | T243: =IFERROR(N243/MEDIAN(INDEX($N$5:$N$665,MATCH($A243-90,$A$5:$A$665,1)):INDEX($N$5:$N$665,MATCH($A243+90,$A$5:$A$665,1))),"") -> 0.99986112 | U243: =IFERROR(Q243/MEDIAN(INDEX($Q$5:$Q$665,MATCH($A243-90,$A$5:$A$665,1)):INDEX($Q$5:$Q$665,MATCH($A243+90,$A$5:$A$665,1))),"") -> 0.23782002
A244: 45170.779 | B244: 18 | C244: пт | D244: Этикет в спортзале | E244: ссылка | F244: 31450 | G244: 9749 | H244: 9742 | I244: 1485 | J244: 273 | K244: 10 | L244: 5 | M244: =IFERROR(G244/F244,"") -> 0.3099841 | N244: =IFERROR(H244/G244,"") -> 0.99928198 | O244: =IFERROR(I244/H244,"") -> 0.15243277 | P244: =IFERROR(J244/H244,"") -> 0.028022993 | Q244: =IFERROR(K244/H244,"") -> 0.0010264833 | R244: =IFERROR(L244/H244,"") -> 0.00051324163 | S244: =IFERROR(M244/MEDIAN(INDEX($M$5:$M$665,MATCH($A244-90,$A$5:$A$665,1)):INDEX($M$5:$M$665,MATCH($A244+90,$A$5:$A$665,1))),"") -> 0.726691 | T244: =IFERROR(N244/MEDIAN(INDEX($N$5:$N$665,MATCH($A244-90,$A$5:$A$665,1)):INDEX($N$5:$N$665,MATCH($A244+90,$A$5:$A$665,1))),"") -> 0.99962826 | U244: =IFERROR(Q244/MEDIAN(INDEX($Q$5:$Q$665,MATCH($A244-90,$A$5:$A$665,1)):INDEX($Q$5:$Q$665,MATCH($A244+90,$A$5:$A$665,1))),"") -> 1.0033874
A245: 45171.719 | B245: 17 | C245: сб | D245: Наслаждайтесь капучино, а не издевайтесь над ним☕️ | E245: ссылка | F245: 35275 | G245: 16257 | H245: 16250 | I245: 3244 | J245: 316 | K245: 14 | L245: 9 | M245: =IFERROR(G245/F245,"") -> 0.46086464 | N245: =IFERROR(H245/G245,"") -> 0.99956942 | O245: =IFERROR(I245/H245,"") -> 0.19963077 | P245: =IFERROR(J245/H245,"") -> 0.019446154 | Q245: =IFERROR(K245/H245,"") -> 0.00086153846 | R245: =IFERROR(L245/H245,"") -> 0.00055384615 | S245: =IFERROR(M245/MEDIAN(INDEX($M$5:$M$665,MATCH($A245-90,$A$5:$A$665,1)):INDEX($M$5:$M$665,MATCH($A245+90,$A$5:$A$665,1))),"") -> 1.0809208 | T245: =IFERROR(N245/MEDIAN(INDEX($N$5:$N$665,MATCH($A245-90,$A$5:$A$665,1)):INDEX($N$5:$N$665,MATCH($A245+90,$A$5:$A$665,1))),"") -> 0.99991039 | U245: =IFERROR(Q245/MEDIAN(INDEX($Q$5:$Q$665,MATCH($A245-90,$A$5:$A$665,1)):INDEX($Q$5:$Q$665,MATCH($A245+90,$A$5:$A$665,1))),"") -> 0.84311219
A246: 45172.708 | B246: 16 | C246: вс | D246: Как правильно показывать пальцем? | E246: ссылка | F246: 12843 | G246: 8326 | H246: 8320 | I246: 1967 | J246: 291 | K246: 5 | L246: 13 | M246: =IFERROR(G246/F246,"") -> 0.6482909 | N246: =IFERROR(H246/G246,"") -> 0.99927937 | O246: =IFERROR(I246/H246,"") -> 0.23641827 | P246: =IFERROR(J246/H246,"") -> 0.034975962 | Q246: =IFERROR(K246/H246,"") -> 0.00060096154 | R246: =IFERROR(L246/H246,"") -> 0.0015625 | S246: =IFERROR(M246/MEDIAN(INDEX($M$5:$M$665,MATCH($A246-90,$A$5:$A$665,1)):INDEX($M$5:$M$665,MATCH($A246+90,$A$5:$A$665,1))),"") -> 1.520514 | T246: =IFERROR(N246/MEDIAN(INDEX($N$5:$N$665,MATCH($A246-90,$A$5:$A$665,1)):INDEX($N$5:$N$665,MATCH($A246+90,$A$5:$A$665,1))),"") -> 0.99961231 | U246: =IFERROR(Q246/MEDIAN(INDEX($Q$5:$Q$665,MATCH($A246-90,$A$5:$A$665,1)):INDEX($Q$5:$Q$665,MATCH($A246+90,$A$5:$A$665,1))),"") -> 0.58810839
A247: 45173.731 | B247: 17 | C247: пн | D247: Как сидеть красиво | E247: ссылка | F247: 362849 | G247: 88206 | H247: 88203 | I247: 8035 | J247: 362 | K247: 12 | L247: 35 | M247: =IFERROR(G247/F247,"") -> 0.24309286 | N247: =IFERROR(H247/G247,"") -> 0.99996599 | O247: =IFERROR(I247/H247,"") -> 0.091096675 | P247: =IFERROR(J247/H247,"") -> 0.0041041688 | Q247: =IFERROR(K247/H247,"") -> 0.00013604979 | R247: =IFERROR(L247/H247,"") -> 0.0003968119 | S247: =IFERROR(M247/MEDIAN(INDEX($M$5:$M$665,MATCH($A247-90,$A$5:$A$665,1)):INDEX($M$5:$M$665,MATCH($A247+90,$A$5:$A$665,1))),"") -> 0.57438166 | T247: =IFERROR(N247/MEDIAN(INDEX($N$5:$N$665,MATCH($A247-90,$A$5:$A$665,1)):INDEX($N$5:$N$665,MATCH($A247+90,$A$5:$A$665,1))),"") -> 1.0002966 | U247: =IFERROR(Q247/MEDIAN(INDEX($Q$5:$Q$665,MATCH($A247-90,$A$5:$A$665,1)):INDEX($Q$5:$Q$665,MATCH($A247+90,$A$5:$A$665,1))),"") -> 0.13329169
A248: 45174.723 | B248: 17 | C248: вт | D248: Кто перезванивает? | E248: ссылка | F248: 10970 | G248: 6083 | H248: 6075 | I248: 1040 | J248: 315 | K248: 6 | L248: 10 | M248: =IFERROR(G248/F248,"") -> 0.55451231 | N248: =IFERROR(H248/G248,"") -> 0.99868486 | O248: =IFERROR(I248/H248,"") -> 0.17119342 | P248: =IFERROR(J248/H248,"") -> 0.051851852 | Q248: =IFERROR(K248/H248,"") -> 0.00098765432 | R248: =IFERROR(L248/H248,"") -> 0.0016460905 | S248: =IFERROR(M248/MEDIAN(INDEX($M$5:$M$665,MATCH($A248-90,$A$5:$A$665,1)):INDEX($M$5:$M$665,MATCH($A248+90,$A$5:$A$665,1))),"") -> 1.3102059 | T248: =IFERROR(N248/MEDIAN(INDEX($N$5:$N$665,MATCH($A248-90,$A$5:$A$665,1)):INDEX($N$5:$N$665,MATCH($A248+90,$A$5:$A$665,1))),"") -> 0.99901509 | U248: =IFERROR(Q248/MEDIAN(INDEX($Q$5:$Q$665,MATCH($A248-90,$A$5:$A$665,1)):INDEX($Q$5:$Q$665,MATCH($A248+90,$A$5:$A$665,1))),"") -> 0.96763187
A249: 45175.794 | B249: 19 | C249: ср | D249: Долгая поездка | E249: ссылка | F249: 101592 | G249: 28033 | H249: 28021 | I249: 3122 | J249: 197 | K249: 13 | L249: 10 | M249: =IFERROR(G249/F249,"") -> 0.27593708 | N249: =IFERROR(H249/G249,"") -> 0.99957193 | O249: =IFERROR(I249/H249,"") -> 0.11141644 | P249: =IFERROR(J249/H249,"") -> 0.0070304415 | Q249: =IFERROR(K249/H249,"") -> 0.00046393776 | R249: =IFERROR(L249/H249,"") -> 0.0003568752 | S249: =IFERROR(M249/MEDIAN(INDEX($M$5:$M$665,MATCH($A249-90,$A$5:$A$665,1)):INDEX($M$5:$M$665,MATCH($A249+90,$A$5:$A$665,1))),"") -> 0.64718817 | T249: =IFERROR(N249/MEDIAN(INDEX($N$5:$N$665,MATCH($A249-90,$A$5:$A$665,1)):INDEX($N$5:$N$665,MATCH($A249+90,$A$5:$A$665,1))),"") -> 0.99989849 | U249: =IFERROR(Q249/MEDIAN(INDEX($Q$5:$Q$665,MATCH($A249-90,$A$5:$A$665,1)):INDEX($Q$5:$Q$665,MATCH($A249+90,$A$5:$A$665,1))),"") -> 0.45862849
A250: 45176.723 | B250: 17 | C250: чт | D250: Не занимйте место сумками | E250: ссылка | F250: 11052 | G250: 6059 | H250: 6055 | I250: 1400 | J250: 275 | K250: 3 | L250: 9 | M250: =IFERROR(G250/F250,"") -> 0.54822657 | N250: =IFERROR(H250/G250,"") -> 0.99933983 | O250: =IFERROR(I250/H250,"") -> 0.23121387 | P250: =IFERROR(J250/H250,"") -> 0.045417011 | Q250: =IFERROR(K250/H250,"") -> 0.0004954583 | R250: =IFERROR(L250/H250,"") -> 0.0014863749 | S250: =IFERROR(M250/MEDIAN(INDEX($M$5:$M$665,MATCH($A250-90,$A$5:$A$665,1)):INDEX($M$5:$M$665,MATCH($A250+90,$A$5:$A$665,1))),"") -> 1.2764277 | T250: =IFERROR(N250/MEDIAN(INDEX($N$5:$N$665,MATCH($A250-90,$A$5:$A$665,1)):INDEX($N$5:$N$665,MATCH($A250+90,$A$5:$A$665,1))),"") -> 0.99967027 | U250: =IFERROR(Q250/MEDIAN(INDEX($Q$5:$Q$665,MATCH($A250-90,$A$5:$A$665,1)):INDEX($Q$5:$Q$665,MATCH($A250+90,$A$5:$A$665,1))),"") -> 0.49424217
A251: 45177.721 | B251: 17 | C251: пт | D251: Рестораы в Китае | E251: ссылка | F251: 37047 | G251: 11004 | H251: 10991 | I251: 1758 | J251: 150 | K251: 5 | L251: 3 | M251: =IFERROR(G251/F251,"") -> 0.2970281 | N251: =IFERROR(H251/G251,"") -> 0.99881861 | O251: =IFERROR(I251/H251,"") -> 0.15994905 | P251: =IFERROR(J251/H251,"") -> 0.01364753 | Q251: =IFERROR(K251/H251,"") -> 0.00045491766 | R251: =IFERROR(L251/H251,"") -> 0.0002729506 | S251: =IFERROR(M251/MEDIAN(INDEX($M$5:$M$665,MATCH($A251-90,$A$5:$A$665,1)):INDEX($M$5:$M$665,MATCH($A251+90,$A$5:$A$665,1))),"") -> 0.70182027 | T251: =IFERROR(N251/MEDIAN(INDEX($N$5:$N$665,MATCH($A251-90,$A$5:$A$665,1)):INDEX($N$5:$N$665,MATCH($A251+90,$A$5:$A$665,1))),"") -> 0.99914097 | U251: =IFERROR(Q251/MEDIAN(INDEX($Q$5:$Q$665,MATCH($A251-90,$A$5:$A$665,1)):INDEX($Q$5:$Q$665,MATCH($A251+90,$A$5:$A$665,1))),"") -> 0.45603428
A252: 45178.729 | B252: 17 | C252: сб | D252: Не кричите на людей | E252: ссылка | F252: 13586 | G252: 6462 | H252: 6455 | I252: 1103 | J252: 282 | K252: 2 | L252: 12 | M252: =IFERROR(G252/F252,"") -> 0.47563668 | N252: =IFERROR(H252/G252,"") -> 0.99891674 | O252: =IFERROR(I252/H252,"") -> 0.17087529 | P252: =IFERROR(J252/H252,"") -> 0.043687064 | Q252: =IFERROR(K252/H252,"") -> 0.00030983734 | R252: =IFERROR(L252/H252,"") -> 0.001859024 | S252: =IFERROR(M252/MEDIAN(INDEX($M$5:$M$665,MATCH($A252-90,$A$5:$A$665,1)):INDEX($M$5:$M$665,MATCH($A252+90,$A$5:$A$665,1))),"") -> 1.123838 | T252: =IFERROR(N252/MEDIAN(INDEX($N$5:$N$665,MATCH($A252-90,$A$5:$A$665,1)):INDEX($N$5:$N$665,MATCH($A252+90,$A$5:$A$665,1))),"") -> 0.99923913 | U252: =IFERROR(Q252/MEDIAN(INDEX($Q$5:$Q$665,MATCH($A252-90,$A$5:$A$665,1)):INDEX($Q$5:$Q$665,MATCH($A252+90,$A$5:$A$665,1))),"") -> 0.3137103
A253: 45179.796 | B253: 19 | C253: вс | E253: ссылка | F253: 3421 | G253: 1256 | H253: 1247 | I253: 289 | J253: 80 | K253: 2 | L253: 2 | M253: =IFERROR(G253/F253,"") -> 0.36714411 | N253: =IFERROR(H253/G253,"") -> 0.99283439 | O253: =IFERROR(I253/H253,"") -> 0.23175621 | P253: =IFERROR(J253/H253,"") -> 0.06415397 | Q253: =IFERROR(K253/H253,"") -> 0.0016038492 | R253: =IFERROR(L253/H253,"") -> 0.0016038492 | S253: =IFERROR(M253/MEDIAN(INDEX($M$5:$M$665,MATCH($A253-90,$A$5:$A$665,1)):INDEX($M$5:$M$665,MATCH($A253+90,$A$5:$A$665,1))),"") -> 0.8682032 | T253: =IFERROR(N253/MEDIAN(INDEX($N$5:$N$665,MATCH($A253-90,$A$5:$A$665,1)):INDEX($N$5:$N$665,MATCH($A253+90,$A$5:$A$665,1))),"") -> 0.99315876 | U253: =IFERROR(Q253/MEDIAN(INDEX($Q$5:$Q$665,MATCH($A253-90,$A$5:$A$665,1)):INDEX($Q$5:$Q$665,MATCH($A253+90,$A$5:$A$665,1))),"") -> 1.6158015
A254: 45180.741 | B254: 17 | C254: пн | D254: Знакомства на улице | E254: ссылка | F254: 7608 | G254: 3962 | H254: 3961 | I254: 1192 | J254: 286 | K254: 16 | L254: 6 | M254: =IFERROR(G254/F254,"") -> 0.52076761 | N254: =IFERROR(H254/G254,"") -> 0.9997476 | O254: =IFERROR(I254/H254,"") -> 0.30093411 | P254: =IFERROR(J254/H254,"") -> 0.072203989 | Q254: =IFERROR(K254/H254,"") -> 0.004039384 | R254: =IFERROR(L254/H254,"") -> 0.001514769 | S254: =IFERROR(M254/MEDIAN(INDEX($M$5:$M$665,MATCH($A254-90,$A$5:$A$665,1)):INDEX($M$5:$M$665,MATCH($A254+90,$A$5:$A$665,1))),"") -> 1.2382848 | T254: =IFERROR(N254/MEDIAN(INDEX($N$5:$N$665,MATCH($A254-90,$A$5:$A$665,1)):INDEX($N$5:$N$665,MATCH($A254+90,$A$5:$A$665,1))),"") -> 1.0000683 | U254: =IFERROR(Q254/MEDIAN(INDEX($Q$5:$Q$665,MATCH($A254-90,$A$5:$A$665,1)):INDEX($Q$5:$Q$665,MATCH($A254+90,$A$5:$A$665,1))),"") -> 4.1046339
A255: 45181.678 | B255: 16 | C255: вт | D255: Испепеляющая взглядом | E255: ссылка | F255: 7883 | G255: 3801 | H255: 3799 | I255: 807 | J255: 203 | K255: 3 | L255: 3 | M255: =IFERROR(G255/F255,"") -> 0.48217684 | N255: =IFERROR(H255/G255,"") -> 0.99947382 | O255: =IFERROR(I255/H255,"") -> 0.21242432 | P255: =IFERROR(J255/H255,"") -> 0.053435114 | Q255: =IFERROR(K255/H255,"") -> 0.0007896815 | R255: =IFERROR(L255/H255,"") -> 0.0007896815 | S255: =IFERROR(M255/MEDIAN(INDEX($M$5:$M$665,MATCH($A255-90,$A$5:$A$665,1)):INDEX($M$5:$M$665,MATCH($A255+90,$A$5:$A$665,1))),"") -> 1.1519337 | T255: =IFERROR(N255/MEDIAN(INDEX($N$5:$N$665,MATCH($A255-90,$A$5:$A$665,1)):INDEX($N$5:$N$665,MATCH($A255+90,$A$5:$A$665,1))),"") -> 0.99979252 | U255: =IFERROR(Q255/MEDIAN(INDEX($Q$5:$Q$665,MATCH($A255-90,$A$5:$A$665,1)):INDEX($Q$5:$Q$665,MATCH($A255+90,$A$5:$A$665,1))),"") -> 0.80534351
A256: 45182.73 | B256: 17 | C256: ср | D256: Еда в поезде | E256: ссылка | F256: 7211 | G256: 3578 | H256: 3572 | I256: 574 | J256: 204 | K256: 2 | L256: 0 | M256: =IFERROR(G256/F256,"") -> 0.49618638 | N256: =IFERROR(H256/G256,"") -> 0.99832309 | O256: =IFERROR(I256/H256,"") -> 0.16069429 | P256: =IFERROR(J256/H256,"") -> 0.057110862 | Q256: =IFERROR(K256/H256,"") -> 0.00055991041 | R256: =IFERROR(L256/H256,"") -> 0 | S256: =IFERROR(M256/MEDIAN(INDEX($M$5:$M$665,MATCH($A256-90,$A$5:$A$665,1)):INDEX($M$5:$M$665,MATCH($A256+90,$A$5:$A$665,1))),"") -> 1.1854029 | T256: =IFERROR(N256/MEDIAN(INDEX($N$5:$N$665,MATCH($A256-90,$A$5:$A$665,1)):INDEX($N$5:$N$665,MATCH($A256+90,$A$5:$A$665,1))),"") -> 0.99862866 | U256: =IFERROR(Q256/MEDIAN(INDEX($Q$5:$Q$665,MATCH($A256-90,$A$5:$A$665,1)):INDEX($Q$5:$Q$665,MATCH($A256+90,$A$5:$A$665,1))),"") -> 0.5774776
A257: 45183.772 | B257: 18 | C257: чт | D257: Оптимальное время ответа на электронное письмо | E257: ссылка | F257: 7826 | G257: 3408 | H257: 3417 | I257: 579 | J257: 240 | K257: 4 | L257: 7 | M257: =IFERROR(G257/F257,"") -> 0.43547151 | N257: =IFERROR(H257/G257,"") -> 1.0026408 | O257: =IFERROR(I257/H257,"") -> 0.16944688 | P257: =IFERROR(J257/H257,"") -> 0.07023705 | Q257: =IFERROR(K257/H257,"") -> 0.0011706175 | R257: =IFERROR(L257/H257,"") -> 0.0020485806 | S257: =IFERROR(M257/MEDIAN(INDEX($M$5:$M$665,MATCH($A257-90,$A$5:$A$665,1)):INDEX($M$5:$M$665,MATCH($A257+90,$A$5:$A$665,1))),"") -> 1.0415139 | T257: =IFERROR(N257/MEDIAN(INDEX($N$5:$N$665,MATCH($A257-90,$A$5:$A$665,1)):INDEX($N$5:$N$665,MATCH($A257+90,$A$5:$A$665,1))),"") -> 1.0029561 | U257: =IFERROR(Q257/MEDIAN(INDEX($Q$5:$Q$665,MATCH($A257-90,$A$5:$A$665,1)):INDEX($Q$5:$Q$665,MATCH($A257+90,$A$5:$A$665,1))),"") -> 1.2335191
A258: 45184.795 | B258: 19 | C258: пт | D258: Закон или этикет | E258: ссылка | F258: 5708 | G258: 2856 | H258: 2846 | I258: 586 | J258: 214 | K258: 3 | L258: 3 | M258: =IFERROR(G258/F258,"") -> 0.50035039 | N258: =IFERROR(H258/G258,"") -> 0.9964986 | O258: =IFERROR(I258/H258,"") -> 0.20590302 | P258: =IFERROR(J258/H258,"") -> 0.075193254 | Q258: =IFERROR(K258/H258,"") -> 0.001054111 | R258: =IFERROR(L258/H258,"") -> 0.001054111 | S258: =IFERROR(M258/MEDIAN(INDEX($M$5:$M$665,MATCH($A258-90,$A$5:$A$665,1)):INDEX($M$5:$M$665,MATCH($A258+90,$A$5:$A$665,1))),"") -> 1.1996555 | T258: =IFERROR(N258/MEDIAN(INDEX($N$5:$N$665,MATCH($A258-90,$A$5:$A$665,1)):INDEX($N$5:$N$665,MATCH($A258+90,$A$5:$A$665,1))),"") -> 0.99679828 | U258: =IFERROR(Q258/MEDIAN(INDEX($Q$5:$Q$665,MATCH($A258-90,$A$5:$A$665,1)):INDEX($Q$5:$Q$665,MATCH($A258+90,$A$5:$A$665,1))),"") -> 1.1107523
A259: 45185.809 | B259: 19 | C259: сб | D259: Дресс-код в городе | E259: ссылка | F259: 216237 | G259: 41855 | H259: 41855 | I259: 4005 | J259: 372 | K259: 16 | L259: 27 | M259: =IFERROR(G259/F259,"") -> 0.19356077 | N259: =IFERROR(H259/G259,"") -> 1 | O259: =IFERROR(I259/H259,"") -> 0.095687493 | P259: =IFERROR(J259/H259,"") -> 0.008887827 | Q259: =IFERROR(K259/H259,"") -> 0.00038227213 | R259: =IFERROR(L259/H259,"") -> 0.00064508422 | S259: =IFERROR(M259/MEDIAN(INDEX($M$5:$M$665,MATCH($A259-90,$A$5:$A$665,1)):INDEX($M$5:$M$665,MATCH($A259+90,$A$5:$A$665,1))),"") -> 0.4647215 | T259: =IFERROR(N259/MEDIAN(INDEX($N$5:$N$665,MATCH($A259-90,$A$5:$A$665,1)):INDEX($N$5:$N$665,MATCH($A259+90,$A$5:$A$665,1))),"") -> 1.0003061 | U259: =IFERROR(Q259/MEDIAN(INDEX($Q$5:$Q$665,MATCH($A259-90,$A$5:$A$665,1)):INDEX($Q$5:$Q$665,MATCH($A259+90,$A$5:$A$665,1))),"") -> 0.41173894
A260: 45186.777 | B260: 18 | C260: вс | D260: В диалоге | E260: ссылка | F260: 23263 | G260: 10783 | H260: 10777 | I260: 2599 | J260: 283 | K260: 11 | L260: 19 | M260: =IFERROR(G260/F260,"") -> 0.46352577 | N260: =IFERROR(H260/G260,"") -> 0.99944357 | O260: =IFERROR(I260/H260,"") -> 0.24116173 | P260: =IFERROR(J260/H260,"") -> 0.026259627 | Q260: =IFERROR(K260/H260,"") -> 0.0010206922 | R260: =IFERROR(L260/H260,"") -> 0.0017630138 | S260: =IFERROR(M260/MEDIAN(INDEX($M$5:$M$665,MATCH($A260-90,$A$5:$A$665,1)):INDEX($M$5:$M$665,MATCH($A260+90,$A$5:$A$665,1))),"") -> 1.1133369 | T260: =IFERROR(N260/MEDIAN(INDEX($N$5:$N$665,MATCH($A260-90,$A$5:$A$665,1)):INDEX($N$5:$N$665,MATCH($A260+90,$A$5:$A$665,1))),"") -> 0.99974949 | U260: =IFERROR(Q260/MEDIAN(INDEX($Q$5:$Q$665,MATCH($A260-90,$A$5:$A$665,1)):INDEX($Q$5:$Q$665,MATCH($A260+90,$A$5:$A$665,1))),"") -> 1.0527164
A261: 45187.79 | B261: 18 | C261: пн | D261: Рюкзаки | E261: ссылка | F261: 25721 | G261: 15126 | H261: 15121 | I261: 1917 | J261: 348 | K261: 21 | L261: 4 | M261: =IFERROR(G261/F261,"") -> 0.58807978 | N261: =IFERROR(H261/G261,"") -> 0.99966944 | O261: =IFERROR(I261/H261,"") -> 0.12677733 | P261: =IFERROR(J261/H261,"") -> 0.023014351 | Q261: =IFERROR(K261/H261,"") -> 0.001388797 | R261: =IFERROR(L261/H261,"") -> 0.00026453277 | S261: =IFERROR(M261/MEDIAN(INDEX($M$5:$M$665,MATCH($A261-90,$A$5:$A$665,1)):INDEX($M$5:$M$665,MATCH($A261+90,$A$5:$A$665,1))),"") -> 1.4157476 | T261: =IFERROR(N261/MEDIAN(INDEX($N$5:$N$665,MATCH($A261-90,$A$5:$A$665,1)):INDEX($N$5:$N$665,MATCH($A261+90,$A$5:$A$665,1))),"") -> 0.99997543 | U261: =IFERROR(Q261/MEDIAN(INDEX($Q$5:$Q$665,MATCH($A261-90,$A$5:$A$665,1)):INDEX($Q$5:$Q$665,MATCH($A261+90,$A$5:$A$665,1))),"") -> 1.4323705
A262: 45188.78 | B262: 18 | C262: вт | D262: Нет наушников - нет музыки | E262: ссылка | F262: 5184 | G262: 2194 | H262: 2184 | I262: 427 | J262: 195 | K262: 7 | L262: 3 | M262: =IFERROR(G262/F262,"") -> 0.42322531 | N262: =IFERROR(H262/G262,"") -> 0.99544211 | O262: =IFERROR(I262/H262,"") -> 0.19551282 | P262: =IFERROR(J262/H262,"") -> 0.089285714 | Q262: =IFERROR(K262/H262,"") -> 0.0032051282 | R262: =IFERROR(L262/H262,"") -> 0.0013736264 | S262: =IFERROR(M262/MEDIAN(INDEX($M$5:$M$665,MATCH($A262-90,$A$5:$A$665,1)):INDEX($M$5:$M$665,MATCH($A262+90,$A$5:$A$665,1))),"") -> 1.0317484 | T262: =IFERROR(N262/MEDIAN(INDEX($N$5:$N$665,MATCH($A262-90,$A$5:$A$665,1)):INDEX($N$5:$N$665,MATCH($A262+90,$A$5:$A$665,1))),"") -> 0.99573615 | U262: =IFERROR(Q262/MEDIAN(INDEX($Q$5:$Q$665,MATCH($A262-90,$A$5:$A$665,1)):INDEX($Q$5:$Q$665,MATCH($A262+90,$A$5:$A$665,1))),"") -> 3.4521902
A263: 45189.667 | B263: 15 | C263: ср | D263: Сетевой этикет, также известный как «Netiquette» (от английских слов «network» и «etiquette») | E263: ссылка | F263: 6717 | G263: 2704 | H263: 2701 | I263: 578 | J263: 163 | K263: 2 | L263: 0 | M263: =IFERROR(G263/F263,"") -> 0.40256067 | N263: =IFERROR(H263/G263,"") -> 0.99889053 | O263: =IFERROR(I263/H263,"") -> 0.21399482 | P263: =IFERROR(J263/H263,"") -> 0.060348019 | Q263: =IFERROR(K263/H263,"") -> 0.00074046649 | R263: =IFERROR(L263/H263,"") -> 0 | S263: =IFERROR(M263/MEDIAN(INDEX($M$5:$M$665,MATCH($A263-90,$A$5:$A$665,1)):INDEX($M$5:$M$665,MATCH($A263+90,$A$5:$A$665,1))),"") -> 0.98137162 | T263: =IFERROR(N263/MEDIAN(INDEX($N$5:$N$665,MATCH($A263-90,$A$5:$A$665,1)):INDEX($N$5:$N$665,MATCH($A263+90,$A$5:$A$665,1))),"") -> 0.99918558 | U263: =IFERROR(Q263/MEDIAN(INDEX($Q$5:$Q$665,MATCH($A263-90,$A$5:$A$665,1)):INDEX($Q$5:$Q$665,MATCH($A263+90,$A$5:$A$665,1))),"") -> 0.79754412
A264: 45190.667 | B264: 15 | C264: чт | D264: Деловой макияж | E264: ссылка | F264: 8821 | G264: 2787 | H264: 2807 | I264: 1003 | J264: 196 | K264: 6 | L264: 7 | M264: =IFERROR(G264/F264,"") -> 0.31595057 | N264: =IFERROR(H264/G264,"") -> 1.0071762 | O264: =IFERROR(I264/H264,"") -> 0.35732098 | P264: =IFERROR(J264/H264,"") -> 0.069825436 | Q264: =IFERROR(K264/H264,"") -> 0.0021375134 | R264: =IFERROR(L264/H264,"") -> 0.0024937656 | S264: =IFERROR(M264/MEDIAN(INDEX($M$5:$M$665,MATCH($A264-90,$A$5:$A$665,1)):INDEX($M$5:$M$665,MATCH($A264+90,$A$5:$A$665,1))),"") -> 0.77023155 | T264: =IFERROR(N264/MEDIAN(INDEX($N$5:$N$665,MATCH($A264-90,$A$5:$A$665,1)):INDEX($N$5:$N$665,MATCH($A264+90,$A$5:$A$665,1))),"") -> 1.0074845 | U264: =IFERROR(Q264/MEDIAN(INDEX($Q$5:$Q$665,MATCH($A264-90,$A$5:$A$665,1)):INDEX($Q$5:$Q$665,MATCH($A264+90,$A$5:$A$665,1))),"") -> 2.3111863
A265: 45191.667 | B265: 16 | C265: пт | D265: Наводить красоту | E265: ссылка | F265: 39549 | G265: 11387 | H265: 11389 | I265: 1715 | J265: 248 | K265: 6 | L265: 4 | M265: =IFERROR(G265/F265,"") -> 0.28792131 | N265: =IFERROR(H265/G265,"") -> 1.0001756 | O265: =IFERROR(I265/H265,"") -> 0.1505839 | P265: =IFERROR(J265/H265,"") -> 0.021775397 | Q265: =IFERROR(K265/H265,"") -> 0.00052682413 | R265: =IFERROR(L265/H265,"") -> 0.00035121609 | S265: =IFERROR(M265/MEDIAN(INDEX($M$5:$M$665,MATCH($A265-90,$A$5:$A$665,1)):INDEX($M$5:$M$665,MATCH($A265+90,$A$5:$A$665,1))),"") -> 0.69749505 | T265: =IFERROR(N265/MEDIAN(INDEX($N$5:$N$665,MATCH($A265-90,$A$5:$A$665,1)):INDEX($N$5:$N$665,MATCH($A265+90,$A$5:$A$665,1))),"") -> 1.0004758 | U265: =IFERROR(Q265/MEDIAN(INDEX($Q$5:$Q$665,MATCH($A265-90,$A$5:$A$665,1)):INDEX($Q$5:$Q$665,MATCH($A265+90,$A$5:$A$665,1))),"") -> 0.57013302
... A523: 45944.292 | B523: 7 | C523: вт | D523: Как вкусно поужинать | E523: ссылка | F523: 763104 | G523: 33366 | H523: 79909 | I523: 0 | J523: 87 | K523: 3 | L523: 12 | M523: =IFERROR(G523/F523,"") -> 0.043724053 | N523: =IFERROR(H523/G523,"") -> 2.394923 | O523: =IFERROR(I523/H523,"") -> 0 | P523: =IFERROR(J523/H523,"") -> 0.0010887384 | Q523: =IFERROR(K523/H523,"") -> 3.7542705e-05 | R523: =IFERROR(L523/H523,"") -> 0.00015017082 | S523: =IFERROR(M523/MEDIAN(INDEX($M$5:$M$665,MATCH($A523-90,$A$5:$A$665,1)):INDEX($M$5:$M$665,MATCH($A523+90,$A$5:$A$665,1))),"") -> 0.15077764 | T523: =IFERROR(N523/MEDIAN(INDEX($N$5:$N$665,MATCH($A523-90,$A$5:$A$665,1)):INDEX($N$5:$N$665,MATCH($A523+90,$A$5:$A$665,1))),"") -> 3.4068236 | U523: =IFERROR(Q523/MEDIAN(INDEX($Q$5:$Q$665,MATCH($A523-90,$A$5:$A$665,1)):INDEX($Q$5:$Q$665,MATCH($A523+90,$A$5:$A$665,1))),"") -> 0.1414593
A524: 45950.85 | B524: 20 | C524: пн | E524: ссылка | F524: 826230 | G524: 64297 | H524: 147076 | I524: 0 | J524: 82 | K524: 21 | L524: 6 | M524: =IFERROR(G524/F524,"") -> 0.077819735 | N524: =IFERROR(H524/G524,"") -> 2.2874473 | O524: =IFERROR(I524/H524,"") -> 0 | P524: =IFERROR(J524/H524,"") -> 0.00055753488 | Q524: =IFERROR(K524/H524,"") -> 0.00014278332 | R524: =IFERROR(L524/H524,"") -> 4.0795235e-05 | S524: =IFERROR(M524/MEDIAN(INDEX($M$5:$M$665,MATCH($A524-90,$A$5:$A$665,1)):INDEX($M$5:$M$665,MATCH($A524+90,$A$5:$A$665,1))),"") -> 0.24563112 | T524: =IFERROR(N524/MEDIAN(INDEX($N$5:$N$665,MATCH($A524-90,$A$5:$A$665,1)):INDEX($N$5:$N$665,MATCH($A524+90,$A$5:$A$665,1))),"") -> 3.3479172 | U524: =IFERROR(Q524/MEDIAN(INDEX($Q$5:$Q$665,MATCH($A524-90,$A$5:$A$665,1)):INDEX($Q$5:$Q$665,MATCH($A524+90,$A$5:$A$665,1))),"") -> 0.6098929
A525: 45952.688 | B525: 16 | C525: ср | E525: ссылка | F525: 732454 | G525: 83737 | H525: 118787 | I525: 0 | J525: 91 | K525: 2 | L525: 9 | M525: =IFERROR(G525/F525,"") -> 0.1143239 | N525: =IFERROR(H525/G525,"") -> 1.4185724 | O525: =IFERROR(I525/H525,"") -> 0 | P525: =IFERROR(J525/H525,"") -> 0.0007660771 | Q525: =IFERROR(K525/H525,"") -> 1.6836859e-05 | R525: =IFERROR(L525/H525,"") -> 7.5765867e-05 | S525: =IFERROR(M525/MEDIAN(INDEX($M$5:$M$665,MATCH($A525-90,$A$5:$A$665,1)):INDEX($M$5:$M$665,MATCH($A525+90,$A$5:$A$665,1))),"") -> 0.35813024 | T525: =IFERROR(N525/MEDIAN(INDEX($N$5:$N$665,MATCH($A525-90,$A$5:$A$665,1)):INDEX($N$5:$N$665,MATCH($A525+90,$A$5:$A$665,1))),"") -> 2.0862168 | U525: =IFERROR(Q525/MEDIAN(INDEX($Q$5:$Q$665,MATCH($A525-90,$A$5:$A$665,1)):INDEX($Q$5:$Q$665,MATCH($A525+90,$A$5:$A$665,1))),"") -> 0.070176029
A526: 45955.042 | B526: 0 | C526: сб | E526: ссылка | F526: 28656 | G526: 10621 | H526: 7222 | I526: 0 | J526: 63 | K526: 1 | L526: 6 | M526: =IFERROR(G526/F526,"") -> 0.37063791 | N526: =IFERROR(H526/G526,"") -> 0.67997364 | O526: =IFERROR(I526/H526,"") -> 0 | P526: =IFERROR(J526/H526,"") -> 0.0087233453 | Q526: =IFERROR(K526/H526,"") -> 0.0001384658 | R526: =IFERROR(L526/H526,"") -> 0.00083079479 | S526: =IFERROR(M526/MEDIAN(INDEX($M$5:$M$665,MATCH($A526-90,$A$5:$A$665,1)):INDEX($M$5:$M$665,MATCH($A526+90,$A$5:$A$665,1))),"") -> 1.1479294 | T526: =IFERROR(N526/MEDIAN(INDEX($N$5:$N$665,MATCH($A526-90,$A$5:$A$665,1)):INDEX($N$5:$N$665,MATCH($A526+90,$A$5:$A$665,1))),"") -> 1.0015425 | U526: =IFERROR(Q526/MEDIAN(INDEX($Q$5:$Q$665,MATCH($A526-90,$A$5:$A$665,1)):INDEX($Q$5:$Q$665,MATCH($A526+90,$A$5:$A$665,1))),"") -> 0.59145078
A527: 45955.292 | B527: 6 | C527: сб | E527: ссылка | F527: 300089 | G527: 98844 | H527: 67858 | I527: 0 | J527: 160 | K527: 26 | L527: 22 | M527: =IFERROR(G527/F527,"") -> 0.32938228 | N527: =IFERROR(H527/G527,"") -> 0.68651613 | O527: =IFERROR(I527/H527,"") -> 0 | P527: =IFERROR(J527/H527,"") -> 0.002357865 | Q527: =IFERROR(K527/H527,"") -> 0.00038315305 | R527: =IFERROR(L527/H527,"") -> 0.00032420643 | S527: =IFERROR(M527/MEDIAN(INDEX($M$5:$M$665,MATCH($A527-90,$A$5:$A$665,1)):INDEX($M$5:$M$665,MATCH($A527+90,$A$5:$A$665,1))),"") -> 1.0201536 | T527: =IFERROR(N527/MEDIAN(INDEX($N$5:$N$665,MATCH($A527-90,$A$5:$A$665,1)):INDEX($N$5:$N$665,MATCH($A527+90,$A$5:$A$665,1))),"") -> 1.011179 | U527: =IFERROR(Q527/MEDIAN(INDEX($Q$5:$Q$665,MATCH($A527-90,$A$5:$A$665,1)):INDEX($Q$5:$Q$665,MATCH($A527+90,$A$5:$A$665,1))),"") -> 1.636622
A528: 45957.815 | B528: 19 | C528: пн | E528: ссылка | F528: 31285 | G528: 8923 | H528: 4473 | I528: 0 | J528: 40 | K528: 3 | L528: 2 | M528: =IFERROR(G528/F528,"") -> 0.28521656 | N528: =IFERROR(H528/G528,"") -> 0.5012888 | O528: =IFERROR(I528/H528,"") -> 0 | P528: =IFERROR(J528/H528,"") -> 0.0089425442 | Q528: =IFERROR(K528/H528,"") -> 0.00067069081 | R528: =IFERROR(L528/H528,"") -> 0.00044712721 | S528: =IFERROR(M528/MEDIAN(INDEX($M$5:$M$665,MATCH($A528-90,$A$5:$A$665,1)):INDEX($M$5:$M$665,MATCH($A528+90,$A$5:$A$665,1))),"") -> 0.89346734 | T528: =IFERROR(N528/MEDIAN(INDEX($N$5:$N$665,MATCH($A528-90,$A$5:$A$665,1)):INDEX($N$5:$N$665,MATCH($A528+90,$A$5:$A$665,1))),"") -> 0.737218 | U528: =IFERROR(Q528/MEDIAN(INDEX($Q$5:$Q$665,MATCH($A528-90,$A$5:$A$665,1)):INDEX($Q$5:$Q$665,MATCH($A528+90,$A$5:$A$665,1))),"") -> 3.6028327
A529: 45959.702 | B529: 16 | C529: ср | E529: ссылка | F529: 10485 | G529: 414 | H529: 1566 | I529: 0 | J529: 21 | K529: 2 | L529: 5 | M529: =IFERROR(G529/F529,"") -> 0.039484979 | N529: =IFERROR(H529/G529,"") -> 3.7826087 | O529: =IFERROR(I529/H529,"") -> 0 | P529: =IFERROR(J529/H529,"") -> 0.013409962 | Q529: =IFERROR(K529/H529,"") -> 0.0012771392 | R529: =IFERROR(L529/H529,"") -> 0.003192848 | S529: =IFERROR(M529/MEDIAN(INDEX($M$5:$M$665,MATCH($A529-90,$A$5:$A$665,1)):INDEX($M$5:$M$665,MATCH($A529+90,$A$5:$A$665,1))),"") -> 0.12092446 | T529: =IFERROR(N529/MEDIAN(INDEX($N$5:$N$665,MATCH($A529-90,$A$5:$A$665,1)):INDEX($N$5:$N$665,MATCH($A529+90,$A$5:$A$665,1))),"") -> 5.5800636 | U529: =IFERROR(Q529/MEDIAN(INDEX($Q$5:$Q$665,MATCH($A529-90,$A$5:$A$665,1)):INDEX($Q$5:$Q$665,MATCH($A529+90,$A$5:$A$665,1))),"") -> 6.8605664
A530: 45961.596 | B530: 14 | C530: пт | E530: ссылка | F530: 8908 | G530: 771 | H530: 1370 | I530: 0 | J530: 28 | K530: 4 | L530: 6 | M530: =IFERROR(G530/F530,"") -> 0.086551414 | N530: =IFERROR(H530/G530,"") -> 1.7769131 | O530: =IFERROR(I530/H530,"") -> 0 | P530: =IFERROR(J530/H530,"") -> 0.020437956 | Q530: =IFERROR(K530/H530,"") -> 0.002919708 | R530: =IFERROR(L530/H530,"") -> 0.004379562 | S530: =IFERROR(M530/MEDIAN(INDEX($M$5:$M$665,MATCH($A530-90,$A$5:$A$665,1)):INDEX($M$5:$M$665,MATCH($A530+90,$A$5:$A$665,1))),"") -> 0.26806462 | T530: =IFERROR(N530/MEDIAN(INDEX($N$5:$N$665,MATCH($A530-90,$A$5:$A$665,1)):INDEX($N$5:$N$665,MATCH($A530+90,$A$5:$A$665,1))),"") -> 2.6713035 | U530: =IFERROR(Q530/MEDIAN(INDEX($Q$5:$Q$665,MATCH($A530-90,$A$5:$A$665,1)):INDEX($Q$5:$Q$665,MATCH($A530+90,$A$5:$A$665,1))),"") -> 15.701912
A531: 45962.776 | B531: 18 | C531: сб | E531: ссылка | F531: 22236 | G531: 7856 | H531: 4883 | I531: 0 | J531: 84 | K531: 6 | L531: 6 | M531: =IFERROR(G531/F531,"") -> 0.35330095 | N531: =IFERROR(H531/G531,"") -> 0.62156314 | O531: =IFERROR(I531/H531,"") -> 0 | P531: =IFERROR(J531/H531,"") -> 0.017202539 | Q531: =IFERROR(K531/H531,"") -> 0.0012287528 | R531: =IFERROR(L531/H531,"") -> 0.0012287528 | S531: =IFERROR(M531/MEDIAN(INDEX($M$5:$M$665,MATCH($A531-90,$A$5:$A$665,1)):INDEX($M$5:$M$665,MATCH($A531+90,$A$5:$A$665,1))),"") -> 1.0819995 | T531: =IFERROR(N531/MEDIAN(INDEX($N$5:$N$665,MATCH($A531-90,$A$5:$A$665,1)):INDEX($N$5:$N$665,MATCH($A531+90,$A$5:$A$665,1))),"") -> 0.95259822 | U531: =IFERROR(Q531/MEDIAN(INDEX($Q$5:$Q$665,MATCH($A531-90,$A$5:$A$665,1)):INDEX($Q$5:$Q$665,MATCH($A531+90,$A$5:$A$665,1))),"") -> 6.6006433
A532: 45964.831 | B532: 19 | C532: пн | E532: ссылка | F532: 9681 | G532: 3508 | H532: 2378 | I532: 0 | J532: 51 | K532: 2 | L532: 2 | M532: =IFERROR(G532/F532,"") -> 0.36235926 | N532: =IFERROR(H532/G532,"") -> 0.67787913 | O532: =IFERROR(I532/H532,"") -> 0 | P532: =IFERROR(J532/H532,"") -> 0.021446594 | Q532: =IFERROR(K532/H532,"") -> 0.00084104289 | R532: =IFERROR(L532/H532,"") -> 0.00084104289 | S532: =IFERROR(M532/MEDIAN(INDEX($M$5:$M$665,MATCH($A532-90,$A$5:$A$665,1)):INDEX($M$5:$M$665,MATCH($A532+90,$A$5:$A$665,1))),"") -> 1.1049083 | T532: =IFERROR(N532/MEDIAN(INDEX($N$5:$N$665,MATCH($A532-90,$A$5:$A$665,1)):INDEX($N$5:$N$665,MATCH($A532+90,$A$5:$A$665,1))),"") -> 1.0414258 | U532: =IFERROR(Q532/MEDIAN(INDEX($Q$5:$Q$665,MATCH($A532-90,$A$5:$A$665,1)):INDEX($Q$5:$Q$665,MATCH($A532+90,$A$5:$A$665,1))),"") -> 3.9478191
A533: 45966.96 | B533: 23 | C533: ср | E533: ссылка | F533: 22179 | G533: 8162 | H533: 5299 | I533: 0 | J533: 45 | K533: 0 | L533: 3 | M533: =IFERROR(G533/F533,"") -> 0.36800577 | N533: =IFERROR(H533/G533,"") -> 0.64922813 | O533: =IFERROR(I533/H533,"") -> 0 | P533: =IFERROR(J533/H533,"") -> 0.0084921683 | Q533: =IFERROR(K533/H533,"") -> 0 | R533: =IFERROR(L533/H533,"") -> 0.00056614456 | S533: =IFERROR(M533/MEDIAN(INDEX($M$5:$M$665,MATCH($A533-90,$A$5:$A$665,1)):INDEX($M$5:$M$665,MATCH($A533+90,$A$5:$A$665,1))),"") -> 1.1172604 | T533: =IFERROR(N533/MEDIAN(INDEX($N$5:$N$665,MATCH($A533-90,$A$5:$A$665,1)):INDEX($N$5:$N$665,MATCH($A533+90,$A$5:$A$665,1))),"") -> 0.99983313 | U533: =IFERROR(Q533/MEDIAN(INDEX($Q$5:$Q$665,MATCH($A533-90,$A$5:$A$665,1)):INDEX($Q$5:$Q$665,MATCH($A533+90,$A$5:$A$665,1))),"") -> 0
A534: 45967.208 | B534: 4 | C534: чт | D534: Каждому блюду свой подход | E534: ссылка | F534: 12676 | G534: 908 | H534: 1711 | I534: 0 | J534: 29 | K534: 4 | L534: 1 | M534: =IFERROR(G534/F534,"") -> 0.071631429 | N534: =IFERROR(H534/G534,"") -> 1.8843612 | O534: =IFERROR(I534/H534,"") -> 0 | P534: =IFERROR(J534/H534,"") -> 0.016949153 | Q534: =IFERROR(K534/H534,"") -> 0.0023378141 | R534: =IFERROR(L534/H534,"") -> 0.00058445354 | S534: =IFERROR(M534/MEDIAN(INDEX($M$5:$M$665,MATCH($A534-90,$A$5:$A$665,1)):INDEX($M$5:$M$665,MATCH($A534+90,$A$5:$A$665,1))),"") -> 0.21747202 | T534: =IFERROR(N534/MEDIAN(INDEX($N$5:$N$665,MATCH($A534-90,$A$5:$A$665,1)):INDEX($N$5:$N$665,MATCH($A534+90,$A$5:$A$665,1))),"") -> 2.9019796 | U534: =IFERROR(Q534/MEDIAN(INDEX($Q$5:$Q$665,MATCH($A534-90,$A$5:$A$665,1)):INDEX($Q$5:$Q$665,MATCH($A534+90,$A$5:$A$665,1))),"") -> 9.7440094
A535: 45968.055 | B535: 1 | C535: пт | E535: ссылка | F535: 29858 | G535: 12203 | H535: 7825 | I535: 0 | J535: 57 | K535: 1 | L535: 7 | M535: =IFERROR(G535/F535,"") -> 0.40870119 | N535: =IFERROR(H535/G535,"") -> 0.64123576 | O535: =IFERROR(I535/H535,"") -> 0 | P535: =IFERROR(J535/H535,"") -> 0.007284345 | Q535: =IFERROR(K535/H535,"") -> 0.00012779553 | R535: =IFERROR(L535/H535,"") -> 0.00089456869 | S535: =IFERROR(M535/MEDIAN(INDEX($M$5:$M$665,MATCH($A535-90,$A$5:$A$665,1)):INDEX($M$5:$M$665,MATCH($A535+90,$A$5:$A$665,1))),"") -> 1.2462145 | T535: =IFERROR(N535/MEDIAN(INDEX($N$5:$N$665,MATCH($A535-90,$A$5:$A$665,1)):INDEX($N$5:$N$665,MATCH($A535+90,$A$5:$A$665,1))),"") -> 0.98513061 | U535: =IFERROR(Q535/MEDIAN(INDEX($Q$5:$Q$665,MATCH($A535-90,$A$5:$A$665,1)):INDEX($Q$5:$Q$665,MATCH($A535+90,$A$5:$A$665,1))),"") -> 0.52899261
A536: 45968.739 | B536: 17 | C536: пт | E536: ссылка | F536: 818946 | G536: 131877 | H536: 147798 | I536: 0 | J536: 194 | K536: 14 | L536: 18 | M536: =IFERROR(G536/F536,"") -> 0.1610326 | N536: =IFERROR(H536/G536,"") -> 1.1207261 | O536: =IFERROR(I536/H536,"") -> 0 | P536: =IFERROR(J536/H536,"") -> 0.0013126023 | Q536: =IFERROR(K536/H536,"") -> 9.472388e-05 | R536: =IFERROR(L536/H536,"") -> 0.00012178785 | S536: =IFERROR(M536/MEDIAN(INDEX($M$5:$M$665,MATCH($A536-90,$A$5:$A$665,1)):INDEX($M$5:$M$665,MATCH($A536+90,$A$5:$A$665,1))),"") -> 0.49102169 | T536: =IFERROR(N536/MEDIAN(INDEX($N$5:$N$665,MATCH($A536-90,$A$5:$A$665,1)):INDEX($N$5:$N$665,MATCH($A536+90,$A$5:$A$665,1))),"") -> 1.7217718 | U536: =IFERROR(Q536/MEDIAN(INDEX($Q$5:$Q$665,MATCH($A536-90,$A$5:$A$665,1)):INDEX($Q$5:$Q$665,MATCH($A536+90,$A$5:$A$665,1))),"") -> 0.39209692
A537: 45970.029 | B537: 0 | C537: вс | E537: ссылка | F537: 686473 | G537: 132176 | H537: 132076 | I537: 0 | J537: 157 | K537: 3 | L537: 32 | M537: =IFERROR(G537/F537,"") -> 0.19254363 | N537: =IFERROR(H537/G537,"") -> 0.99924343 | O537: =IFERROR(I537/H537,"") -> 0 | P537: =IFERROR(J537/H537,"") -> 0.0011887095 | Q537: =IFERROR(K537/H537,"") -> 2.2714195e-05 | R537: =IFERROR(L537/H537,"") -> 0.00024228475 | S537: =IFERROR(M537/MEDIAN(INDEX($M$5:$M$665,MATCH($A537-90,$A$5:$A$665,1)):INDEX($M$5:$M$665,MATCH($A537+90,$A$5:$A$665,1))),"") -> 0.58455975 | T537: =IFERROR(N537/MEDIAN(INDEX($N$5:$N$665,MATCH($A537-90,$A$5:$A$665,1)):INDEX($N$5:$N$665,MATCH($A537+90,$A$5:$A$665,1))),"") -> 1.5388685 | U537: =IFERROR(Q537/MEDIAN(INDEX($Q$5:$Q$665,MATCH($A537-90,$A$5:$A$665,1)):INDEX($Q$5:$Q$665,MATCH($A537+90,$A$5:$A$665,1))),"") -> 0.093380894
A538: 45971.611 | B538: 14 | C538: пн | E538: ссылка | F538: 406356 | G538: 104758 | H538: 74258 | I538: 0 | J538: 113 | K538: 5 | L538: 9 | M538: =IFERROR(G538/F538,"") -> 0.25779858 | N538: =IFERROR(H538/G538,"") -> 0.70885278 | O538: =IFERROR(I538/H538,"") -> 0 | P538: =IFERROR(J538/H538,"") -> 0.0015217216 | Q538: =IFERROR(K538/H538,"") -> 6.7332813e-05 | R538: =IFERROR(L538/H538,"") -> 0.00012119906 | S538: =IFERROR(M538/MEDIAN(INDEX($M$5:$M$665,MATCH($A538-90,$A$5:$A$665,1)):INDEX($M$5:$M$665,MATCH($A538+90,$A$5:$A$665,1))),"") -> 0.77587454 | T538: =IFERROR(N538/MEDIAN(INDEX($N$5:$N$665,MATCH($A538-90,$A$5:$A$665,1)):INDEX($N$5:$N$665,MATCH($A538+90,$A$5:$A$665,1))),"") -> 1.0890107 | U538: =IFERROR(Q538/MEDIAN(INDEX($Q$5:$Q$665,MATCH($A538-90,$A$5:$A$665,1)):INDEX($Q$5:$Q$665,MATCH($A538+90,$A$5:$A$665,1))),"") -> 0.26755216
A539: 45973.622 | B539: 14 | C539: ср | E539: ссылка | F539: 76801 | G539: 40007 | H539: 20573 | I539: 0 | J539: 100 | K539: 3 | L539: 8 | M539: =IFERROR(G539/F539,"") -> 0.5209177 | N539: =IFERROR(H539/G539,"") -> 0.51423501 | O539: =IFERROR(I539/H539,"") -> 0 | P539: =IFERROR(J539/H539,"") -> 0.0048607398 | Q539: =IFERROR(K539/H539,"") -> 0.00014582219 | R539: =IFERROR(L539/H539,"") -> 0.00038885918 | S539: =IFERROR(M539/MEDIAN(INDEX($M$5:$M$665,MATCH($A539-90,$A$5:$A$665,1)):INDEX($M$5:$M$665,MATCH($A539+90,$A$5:$A$665,1))),"") -> 1.5542615 | T539: =IFERROR(N539/MEDIAN(INDEX($N$5:$N$665,MATCH($A539-90,$A$5:$A$665,1)):INDEX($N$5:$N$665,MATCH($A539+90,$A$5:$A$665,1))),"") -> 0.78810876 | U539: =IFERROR(Q539/MEDIAN(INDEX($Q$5:$Q$665,MATCH($A539-90,$A$5:$A$665,1)):INDEX($Q$5:$Q$665,MATCH($A539+90,$A$5:$A$665,1))),"") -> 0.56067703
A540: 45975.979 | B540: 23 | C540: пт | E540: ссылка | F540: 15007 | G540: 5482 | H540: 2203 | I540: 0 | J540: 69 | K540: 2 | L540: 2 | M540: =IFERROR(G540/F540,"") -> 0.3652962 | N540: =IFERROR(H540/G540,"") -> 0.40186063 | O540: =IFERROR(I540/H540,"") -> 0 | P540: =IFERROR(J540/H540,"") -> 0.031320926 | Q540: =IFERROR(K540/H540,"") -> 0.00090785293 | R540: =IFERROR(L540/H540,"") -> 0.00090785293 | S540: =IFERROR(M540/MEDIAN(INDEX($M$5:$M$665,MATCH($A540-90,$A$5:$A$665,1)):INDEX($M$5:$M$665,MATCH($A540+90,$A$5:$A$665,1))),"") -> 1.099401 | T540: =IFERROR(N540/MEDIAN(INDEX($N$5:$N$665,MATCH($A540-90,$A$5:$A$665,1)):INDEX($N$5:$N$665,MATCH($A540+90,$A$5:$A$665,1))),"") -> 0.60413293 | U540: =IFERROR(Q540/MEDIAN(INDEX($Q$5:$Q$665,MATCH($A540-90,$A$5:$A$665,1)):INDEX($Q$5:$Q$665,MATCH($A540+90,$A$5:$A$665,1))),"") -> 3.6074241
A541: 45976.567 | B541: 13 | C541: сб | E541: ссылка | F541: 7839 | G541: 248 | H541: 1081 | I541: 0 | J541: 33 | K541: 2 | L541: 4 | M541: =IFERROR(G541/F541,"") -> 0.031636688 | N541: =IFERROR(H541/G541,"") -> 4.358871 | O541: =IFERROR(I541/H541,"") -> 0 | P541: =IFERROR(J541/H541,"") -> 0.03052729 | Q541: =IFERROR(K541/H541,"") -> 0.0018501388 | R541: =IFERROR(L541/H541,"") -> 0.0037002775 | S541: =IFERROR(M541/MEDIAN(INDEX($M$5:$M$665,MATCH($A541-90,$A$5:$A$665,1)):INDEX($M$5:$M$665,MATCH($A541+90,$A$5:$A$665,1))),"") -> 0.096048543 | T541: =IFERROR(N541/MEDIAN(INDEX($N$5:$N$665,MATCH($A541-90,$A$5:$A$665,1)):INDEX($N$5:$N$665,MATCH($A541+90,$A$5:$A$665,1))),"") -> 6.4301595 | U541: =IFERROR(Q541/MEDIAN(INDEX($Q$5:$Q$665,MATCH($A541-90,$A$5:$A$665,1)):INDEX($Q$5:$Q$665,MATCH($A541+90,$A$5:$A$665,1))),"") -> 7.1136654
A542: 45978.426 | B542: 10 | C542: пн | E542: ссылка | F542: 58442 | G542: 26348 | H542: 11047 | I542: 0 | J542: 72 | K542: 0 | L542: 10 | M542: =IFERROR(G542/F542,"") -> 0.45084015 | N542: =IFERROR(H542/G542,"") -> 0.41927281 | O542: =IFERROR(I542/H542,"") -> 0 | P542: =IFERROR(J542/H542,"") -> 0.0065176066 | Q542: =IFERROR(K542/H542,"") -> 0 | R542: =IFERROR(L542/H542,"") -> 0.00090522314 | S542: =IFERROR(M542/MEDIAN(INDEX($M$5:$M$665,MATCH($A542-90,$A$5:$A$665,1)):INDEX($M$5:$M$665,MATCH($A542+90,$A$5:$A$665,1))),"") -> 1.3568554 | T542: =IFERROR(N542/MEDIAN(INDEX($N$5:$N$665,MATCH($A542-90,$A$5:$A$665,1)):INDEX($N$5:$N$665,MATCH($A542+90,$A$5:$A$665,1))),"") -> 0.63030933 | U542: =IFERROR(Q542/MEDIAN(INDEX($Q$5:$Q$665,MATCH($A542-90,$A$5:$A$665,1)):INDEX($Q$5:$Q$665,MATCH($A542+90,$A$5:$A$665,1))),"") -> 0
A543: 45982.882 | B543: 21 | C543: пт | E543: ссылка | F543: 9743 | G543: 2486 | H543: 1733 | I543: 0 | J543: 49 | K543: 0 | L543: 0 | M543: =IFERROR(G543/F543,"") -> 0.25515755 | N543: =IFERROR(H543/G543,"") -> 0.69710378 | O543: =IFERROR(I543/H543,"") -> 0 | P543: =IFERROR(J543/H543,"") -> 0.028274668 | Q543: =IFERROR(K543/H543,"") -> 0 | R543: =IFERROR(L543/H543,"") -> 0 | S543: =IFERROR(M543/MEDIAN(INDEX($M$5:$M$665,MATCH($A543-90,$A$5:$A$665,1)):INDEX($M$5:$M$665,MATCH($A543+90,$A$5:$A$665,1))),"") -> 0.75373981 | T543: =IFERROR(N543/MEDIAN(INDEX($N$5:$N$665,MATCH($A543-90,$A$5:$A$665,1)):INDEX($N$5:$N$665,MATCH($A543+90,$A$5:$A$665,1))),"") -> 1.0709607 | U543: =IFERROR(Q543/MEDIAN(INDEX($Q$5:$Q$665,MATCH($A543-90,$A$5:$A$665,1)):INDEX($Q$5:$Q$665,MATCH($A543+90,$A$5:$A$665,1))),"") -> 0
A544: 45983.751 | B544: 18 | C544: сб | E544: ссылка | F544: 15470 | G544: 4560 | H544: 3694 | I544: 0 | J544: 61 | K544: 1 | L544: 5 | M544: =IFERROR(G544/F544,"") -> 0.29476406 | N544: =IFERROR(H544/G544,"") -> 0.81008772 | O544: =IFERROR(I544/H544,"") -> 0 | P544: =IFERROR(J544/H544,"") -> 0.016513265 | Q544: =IFERROR(K544/H544,"") -> 0.00027070926 | R544: =IFERROR(L544/H544,"") -> 0.0013535463 | S544: =IFERROR(M544/MEDIAN(INDEX($M$5:$M$665,MATCH($A544-90,$A$5:$A$665,1)):INDEX($M$5:$M$665,MATCH($A544+90,$A$5:$A$665,1))),"") -> 0.86216147 | T544: =IFERROR(N544/MEDIAN(INDEX($N$5:$N$665,MATCH($A544-90,$A$5:$A$665,1)):INDEX($N$5:$N$665,MATCH($A544+90,$A$5:$A$665,1))),"") -> 1.2475623 | U544: =IFERROR(Q544/MEDIAN(INDEX($Q$5:$Q$665,MATCH($A544-90,$A$5:$A$665,1)):INDEX($Q$5:$Q$665,MATCH($A544+90,$A$5:$A$665,1))),"") -> 1.0408598
A545: 45987.683 | B545: 16 | C545: ср | E545: ссылка | F545: 13678 | G545: 5501 | H545: 3572 | I545: 0 | J545: 84 | K545: 0 | L545: 1 | M545: =IFERROR(G545/F545,"") -> 0.40217868 | N545: =IFERROR(H545/G545,"") -> 0.64933648 | O545: =IFERROR(I545/H545,"") -> 0 | P545: =IFERROR(J545/H545,"") -> 0.023516237 | Q545: =IFERROR(K545/H545,"") -> 0 | R545: =IFERROR(L545/H545,"") -> 0.00027995521 | S545: =IFERROR(M545/MEDIAN(INDEX($M$5:$M$665,MATCH($A545-90,$A$5:$A$665,1)):INDEX($M$5:$M$665,MATCH($A545+90,$A$5:$A$665,1))),"") -> 1.1149838 | T545: =IFERROR(N545/MEDIAN(INDEX($N$5:$N$665,MATCH($A545-90,$A$5:$A$665,1)):INDEX($N$5:$N$665,MATCH($A545+90,$A$5:$A$665,1))),"") -> 1.0036223 | U545: =IFERROR(Q545/MEDIAN(INDEX($Q$5:$Q$665,MATCH($A545-90,$A$5:$A$665,1)):INDEX($Q$5:$Q$665,MATCH($A545+90,$A$5:$A$665,1))),"") -> 0
A546: 45989.705 | B546: 16 | C546: пт | E546: ссылка | F546: 5442 | G546: 527 | H546: 682 | I546: 0 | J546: 66 | K546: 2 | L546: 0 | M546: =IFERROR(G546/F546,"") -> 0.096839397 | N546: =IFERROR(H546/G546,"") -> 1.2941176 | O546: =IFERROR(I546/H546,"") -> 0 | P546: =IFERROR(J546/H546,"") -> 0.096774194 | Q546: =IFERROR(K546/H546,"") -> 0.0029325513 | R546: =IFERROR(L546/H546,"") -> 0 | S546: =IFERROR(M546/MEDIAN(INDEX($M$5:$M$665,MATCH($A546-90,$A$5:$A$665,1)):INDEX($M$5:$M$665,MATCH($A546+90,$A$5:$A$665,1))),"") -> 0.26724692 | T546: =IFERROR(N546/MEDIAN(INDEX($N$5:$N$665,MATCH($A546-90,$A$5:$A$665,1)):INDEX($N$5:$N$665,MATCH($A546+90,$A$5:$A$665,1))),"") -> 2.018162 | U546: =IFERROR(Q546/MEDIAN(INDEX($Q$5:$Q$665,MATCH($A546-90,$A$5:$A$665,1)):INDEX($Q$5:$Q$665,MATCH($A546+90,$A$5:$A$665,1))),"") -> 10.451026
... A553: 45999.52 | B553: 12 | C553: пн | E553: ссылка | F553: 77764 | G553: 30351 | H553: 11192 | I553: 0 | J553: 156 | K553: 4 | L553: 2 | M553: =IFERROR(G553/F553,"") -> 0.39029628 | N553: =IFERROR(H553/G553,"") -> 0.36875227 | O553: =IFERROR(I553/H553,"") -> 0 | P553: =IFERROR(J553/H553,"") -> 0.013938528 | Q553: =IFERROR(K553/H553,"") -> 0.00035739814 | R553: =IFERROR(L553/H553,"") -> 0.00017869907 | S553: =IFERROR(M553/MEDIAN(INDEX($M$5:$M$665,MATCH($A553-90,$A$5:$A$665,1)):INDEX($M$5:$M$665,MATCH($A553+90,$A$5:$A$665,1))),"") -> 1.076459 | T553: =IFERROR(N553/MEDIAN(INDEX($N$5:$N$665,MATCH($A553-90,$A$5:$A$665,1)):INDEX($N$5:$N$665,MATCH($A553+90,$A$5:$A$665,1))),"") -> 0.59035016 | U553: =IFERROR(Q553/MEDIAN(INDEX($Q$5:$Q$665,MATCH($A553-90,$A$5:$A$665,1)):INDEX($Q$5:$Q$665,MATCH($A553+90,$A$5:$A$665,1))),"") -> 1.2382845
A554: 46001.514 | B554: 12 | C554: ср | D554: Как испортить о себе впечатление | E554: ссылка | F554: 38620 | G554: 4947 | H554: 5451 | I554: 0 | J554: 106 | K554: 6 | L554: 4 | M554: =IFERROR(G554/F554,"") -> 0.12809425 | N554: =IFERROR(H554/G554,"") -> 1.1018799 | O554: =IFERROR(I554/H554,"") -> 0 | P554: =IFERROR(J554/H554,"") -> 0.019445973 | Q554: =IFERROR(K554/H554,"") -> 0.0011007155 | R554: =IFERROR(L554/H554,"") -> 0.00073381031 | S554: =IFERROR(M554/MEDIAN(INDEX($M$5:$M$665,MATCH($A554-90,$A$5:$A$665,1)):INDEX($M$5:$M$665,MATCH($A554+90,$A$5:$A$665,1))),"") -> 0.35329112 | T554: =IFERROR(N554/MEDIAN(INDEX($N$5:$N$665,MATCH($A554-90,$A$5:$A$665,1)):INDEX($N$5:$N$665,MATCH($A554+90,$A$5:$A$665,1))),"") -> 1.7640434 | U554: =IFERROR(Q554/MEDIAN(INDEX($Q$5:$Q$665,MATCH($A554-90,$A$5:$A$665,1)):INDEX($Q$5:$Q$665,MATCH($A554+90,$A$5:$A$665,1))),"") -> 3.8136708
A555: 46002.508 | B555: 12 | C555: чт | E555: ссылка | F555: 5460 | G555: 2081 | H555: 1073 | I555: 0 | J555: 87 | K555: 0 | L555: 2 | M555: =IFERROR(G555/F555,"") -> 0.38113553 | N555: =IFERROR(H555/G555,"") -> 0.51561749 | O555: =IFERROR(I555/H555,"") -> 0 | P555: =IFERROR(J555/H555,"") -> 0.081081081 | Q555: =IFERROR(K555/H555,"") -> 0 | R555: =IFERROR(L555/H555,"") -> 0.0018639329 | S555: =IFERROR(M555/MEDIAN(INDEX($M$5:$M$665,MATCH($A555-90,$A$5:$A$665,1)):INDEX($M$5:$M$665,MATCH($A555+90,$A$5:$A$665,1))),"") -> 1.0518167 | T555: =IFERROR(N555/MEDIAN(INDEX($N$5:$N$665,MATCH($A555-90,$A$5:$A$665,1)):INDEX($N$5:$N$665,MATCH($A555+90,$A$5:$A$665,1))),"") -> 0.8214353 | U555: =IFERROR(Q555/MEDIAN(INDEX($Q$5:$Q$665,MATCH($A555-90,$A$5:$A$665,1)):INDEX($Q$5:$Q$665,MATCH($A555+90,$A$5:$A$665,1))),"") -> 0
A556: 46003.549 | B556: 13 | C556: пт | E556: ссылка | F556: 3066 | G556: 209 | H556: 390 | I556: 0 | J556: 53 | K556: 2 | L556: 0 | M556: =IFERROR(G556/F556,"") -> 0.068166993 | N556: =IFERROR(H556/G556,"") -> 1.8660287 | O556: =IFERROR(I556/H556,"") -> 0 | P556: =IFERROR(J556/H556,"") -> 0.13589744 | Q556: =IFERROR(K556/H556,"") -> 0.0051282051 | R556: =IFERROR(L556/H556,"") -> 0 | S556: =IFERROR(M556/MEDIAN(INDEX($M$5:$M$665,MATCH($A556-90,$A$5:$A$665,1)):INDEX($M$5:$M$665,MATCH($A556+90,$A$5:$A$665,1))),"") -> 0.18800838 | T556: =IFERROR(N556/MEDIAN(INDEX($N$5:$N$665,MATCH($A556-90,$A$5:$A$665,1)):INDEX($N$5:$N$665,MATCH($A556+90,$A$5:$A$665,1))),"") -> 2.9873995 | U556: =IFERROR(Q556/MEDIAN(INDEX($Q$5:$Q$665,MATCH($A556-90,$A$5:$A$665,1)):INDEX($Q$5:$Q$665,MATCH($A556+90,$A$5:$A$665,1))),"") -> 16.933953
...

Sheet Посты
A1: Посты
A2: Короткие посты. Отдельный лист по той же причине.
A4: Дата публикации | B4: Час | C4: День недели | D4: Заголовок | E4: Ссылка | F4: Показы | G4: Открытия | H4: Дочитывания | I4: Время просмотра, мин | J4: Лайки | K4: Комментарии | L4: Подписки | M4: CTR (открытия/показы) | N4: Дочитываемость | O4: Минут на дочитывание | P4: Лайки / дочитывания | Q4: Комментарии / дочитывания | R4: Подписки / дочитывания | S4: Индекс CTR к периоду | T4: Индекс дочитываемости к периоду | U4: Индекс комментариев к периоду
A5: 44977.689 | B5: 16 | C5: пн | D5: Мастер-класс по имиджу и деловому этикету Если у вас нет планов на 6 марта и… | E5: ссылка | F5: 1059 | G5: 157 | H5: 153 | I5: 8 | J5: 6 | K5: 0 | L5: 0 | M5: =IFERROR(G5/F5,"") -> 0.14825307 | N5: =IFERROR(H5/G5,"") -> 0.97452229 | O5: =IFERROR(I5/H5,"") -> 0.052287582 | P5: =IFERROR(J5/H5,"") -> 0.039215686 | Q5: =IFERROR(K5/H5,"") -> 0 | R5: =IFERROR(L5/H5,"") -> 0 | S5: =IFERROR(M5/MEDIAN(INDEX($M$5:$M$373,MATCH($A5-90,$A$5:$A$373,1)):INDEX($M$5:$M$373,MATCH($A5+90,$A$5:$A$373,1))),"") | T5: =IFERROR(N5/MEDIAN(INDEX($N$5:$N$373,MATCH($A5-90,$A$5:$A$373,1)):INDEX($N$5:$N$373,MATCH($A5+90,$A$5:$A$373,1))),"") | U5: =IFERROR(Q5/MEDIAN(INDEX($Q$5:$Q$373,MATCH($A5-90,$A$5:$A$373,1)):INDEX($Q$5:$Q$373,MATCH($A5+90,$A$5:$A$373,1))),"")
A6: 44979.602 | B6: 14 | C6: ср | D6: Много не бывает! Образований.. Я заканчиваю школу и нервно думаю, куда… | E6: ссылка | F6: 1234 | G6: 367 | H6: 366 | I6: 24 | J6: 17 | K6: 0 | L6: 1 | M6: =IFERROR(G6/F6,"") -> 0.29740681 | N6: =IFERROR(H6/G6,"") -> 0.9972752 | O6: =IFERROR(I6/H6,"") -> 0.06557377 | P6: =IFERROR(J6/H6,"") -> 0.046448087 | Q6: =IFERROR(K6/H6,"") -> 0 | R6: =IFERROR(L6/H6,"") -> 0.0027322404 | S6: =IFERROR(M6/MEDIAN(INDEX($M$5:$M$373,MATCH($A6-90,$A$5:$A$373,1)):INDEX($M$5:$M$373,MATCH($A6+90,$A$5:$A$373,1))),"") | T6: =IFERROR(N6/MEDIAN(INDEX($N$5:$N$373,MATCH($A6-90,$A$5:$A$373,1)):INDEX($N$5:$N$373,MATCH($A6+90,$A$5:$A$373,1))),"") | U6: =IFERROR(Q6/MEDIAN(INDEX($Q$5:$Q$373,MATCH($A6-90,$A$5:$A$373,1)):INDEX($Q$5:$Q$373,MATCH($A6+90,$A$5:$A$373,1))),"")
A7: 44993.851 | B7: 20 | C7: ср | D7: Накануне Международного женского дня прошла конференция «Женщины ДЕЛА… | E7: ссылка | F7: 2405 | G7: 397 | H7: 396 | I7: 1 | J7: 19 | K7: 2 | L7: 2 | M7: =IFERROR(G7/F7,"") -> 0.16507277 | N7: =IFERROR(H7/G7,"") -> 0.99748111 | O7: =IFERROR(I7/H7,"") -> 0.0025252525 | P7: =IFERROR(J7/H7,"") -> 0.047979798 | Q7: =IFERROR(K7/H7,"") -> 0.0050505051 | R7: =IFERROR(L7/H7,"") -> 0.0050505051 | S7: =IFERROR(M7/MEDIAN(INDEX($M$5:$M$373,MATCH($A7-90,$A$5:$A$373,1)):INDEX($M$5:$M$373,MATCH($A7+90,$A$5:$A$373,1))),"") | T7: =IFERROR(N7/MEDIAN(INDEX($N$5:$N$373,MATCH($A7-90,$A$5:$A$373,1)):INDEX($N$5:$N$373,MATCH($A7+90,$A$5:$A$373,1))),"") | U7: =IFERROR(Q7/MEDIAN(INDEX($Q$5:$Q$373,MATCH($A7-90,$A$5:$A$373,1)):INDEX($Q$5:$Q$373,MATCH($A7+90,$A$5:$A$373,1))),"")
A8: 45006.447 | B8: 10 | C8: вт | D8: Новости по социальному проекту Я очень рада поделиться новостями о социальном… | E8: ссылка | F8: 5493 | G8: 663 | H8: 659 | I8: 29 | J8: 42 | K8: 4 | L8: 2 | M8: =IFERROR(G8/F8,"") -> 0.12069907 | N8: =IFERROR(H8/G8,"") -> 0.99396682 | O8: =IFERROR(I8/H8,"") -> 0.04400607 | P8: =IFERROR(J8/H8,"") -> 0.063732929 | Q8: =IFERROR(K8/H8,"") -> 0.0060698027 | R8: =IFERROR(L8/H8,"") -> 0.0030349014 | S8: =IFERROR(M8/MEDIAN(INDEX($M$5:$M$373,MATCH($A8-90,$A$5:$A$373,1)):INDEX($M$5:$M$373,MATCH($A8+90,$A$5:$A$373,1))),"") | T8: =IFERROR(N8/MEDIAN(INDEX($N$5:$N$373,MATCH($A8-90,$A$5:$A$373,1)):INDEX($N$5:$N$373,MATCH($A8+90,$A$5:$A$373,1))),"") | U8: =IFERROR(Q8/MEDIAN(INDEX($Q$5:$Q$373,MATCH($A8-90,$A$5:$A$373,1)):INDEX($Q$5:$Q$373,MATCH($A8+90,$A$5:$A$373,1))),"")
A9: 45010.019 | B9: 0 | C9: сб | D9: Пару дней назад посетила очередную школу со своим проектом «Образ Будущего… | E9: ссылка | F9: 13661 | G9: 1899 | H9: 1896 | I9: 16 | J9: 65 | K9: 11 | L9: 0 | M9: =IFERROR(G9/F9,"") -> 0.13900886 | N9: =IFERROR(H9/G9,"") -> 0.99842022 | O9: =IFERROR(I9/H9,"") -> 0.0084388186 | P9: =IFERROR(J9/H9,"") -> 0.0342827 | Q9: =IFERROR(K9/H9,"") -> 0.0058016878 | R9: =IFERROR(L9/H9,"") -> 0 | S9: =IFERROR(M9/MEDIAN(INDEX($M$5:$M$373,MATCH($A9-90,$A$5:$A$373,1)):INDEX($M$5:$M$373,MATCH($A9+90,$A$5:$A$373,1))),"") | T9: =IFERROR(N9/MEDIAN(INDEX($N$5:$N$373,MATCH($A9-90,$A$5:$A$373,1)):INDEX($N$5:$N$373,MATCH($A9+90,$A$5:$A$373,1))),"") | U9: =IFERROR(Q9/MEDIAN(INDEX($Q$5:$Q$373,MATCH($A9-90,$A$5:$A$373,1)):INDEX($Q$5:$Q$373,MATCH($A9+90,$A$5:$A$373,1))),"")
A10: 45036.262 | B10: 6 | C10: чт | D10: НЕ всегда говори да Многие из нас боятся сказать "нет". Мы переживаем, что… | E10: ссылка | F10: 7280 | G10: 1211 | H10: 1210 | I10: 5 | J10: 32 | K10: 3 | L10: 7 | M10: =IFERROR(G10/F10,"") -> 0.16634615 | N10: =IFERROR(H10/G10,"") -> 0.99917424 | O10: =IFERROR(I10/H10,"") -> 0.0041322314 | P10: =IFERROR(J10/H10,"") -> 0.026446281 | Q10: =IFERROR(K10/H10,"") -> 0.0024793388 | R10: =IFERROR(L10/H10,"") -> 0.005785124 | S10: =IFERROR(M10/MEDIAN(INDEX($M$5:$M$373,MATCH($A10-90,$A$5:$A$373,1)):INDEX($M$5:$M$373,MATCH($A10+90,$A$5:$A$373,1))),"") | T10: =IFERROR(N10/MEDIAN(INDEX($N$5:$N$373,MATCH($A10-90,$A$5:$A$373,1)):INDEX($N$5:$N$373,MATCH($A10+90,$A$5:$A$373,1))),"") | U10: =IFERROR(Q10/MEDIAN(INDEX($Q$5:$Q$373,MATCH($A10-90,$A$5:$A$373,1)):INDEX($Q$5:$Q$373,MATCH($A10+90,$A$5:$A$373,1))),"")
A11: 45037.43 | B11: 10 | C11: пт | D11: Воскресенье - прекрасный день, Чтобы посетить петербургскую ярмарку 💫 Я не… | E11: ссылка | F11: 3457 | G11: 313 | H11: 312 | I11: 2 | J11: 16 | K11: 2 | L11: 0 | M11: =IFERROR(G11/F11,"") -> 0.090540931 | N11: =IFERROR(H11/G11,"") -> 0.99680511 | O11: =IFERROR(I11/H11,"") -> 0.0064102564 | P11: =IFERROR(J11/H11,"") -> 0.051282051 | Q11: =IFERROR(K11/H11,"") -> 0.0064102564 | R11: =IFERROR(L11/H11,"") -> 0 | S11: =IFERROR(M11/MEDIAN(INDEX($M$5:$M$373,MATCH($A11-90,$A$5:$A$373,1)):INDEX($M$5:$M$373,MATCH($A11+90,$A$5:$A$373,1))),"") | T11: =IFERROR(N11/MEDIAN(INDEX($N$5:$N$373,MATCH($A11-90,$A$5:$A$373,1)):INDEX($N$5:$N$373,MATCH($A11+90,$A$5:$A$373,1))),"") | U11: =IFERROR(Q11/MEDIAN(INDEX($Q$5:$Q$373,MATCH($A11-90,$A$5:$A$373,1)):INDEX($Q$5:$Q$373,MATCH($A11+90,$A$5:$A$373,1))),"")
A12: 45040.405 | B12: 9 | C12: пн | D12: Мистер и Мисс Этикет На днях мне прислали ссылку на хранилище с видео от… | E12: ссылка | F12: 4454 | G12: 831 | H12: 830 | I12: 1 | J12: 33 | K12: 3 | L12: 0 | M12: =IFERROR(G12/F12,"") -> 0.18657387 | N12: =IFERROR(H12/G12,"") -> 0.99879663 | O12: =IFERROR(I12/H12,"") -> 0.0012048193 | P12: =IFERROR(J12/H12,"") -> 0.039759036 | Q12: =IFERROR(K12/H12,"") -> 0.0036144578 | R12: =IFERROR(L12/H12,"") -> 0 | S12: =IFERROR(M12/MEDIAN(INDEX($M$5:$M$373,MATCH($A12-90,$A$5:$A$373,1)):INDEX($M$5:$M$373,MATCH($A12+90,$A$5:$A$373,1))),"") | T12: =IFERROR(N12/MEDIAN(INDEX($N$5:$N$373,MATCH($A12-90,$A$5:$A$373,1)):INDEX($N$5:$N$373,MATCH($A12+90,$A$5:$A$373,1))),"") | U12: =IFERROR(Q12/MEDIAN(INDEX($Q$5:$Q$373,MATCH($A12-90,$A$5:$A$373,1)):INDEX($Q$5:$Q$373,MATCH($A12+90,$A$5:$A$373,1))),"")
A13: 45051.379 | B13: 9 | C13: пт | D13: У меня красивая фигура, но зачастую я выбираю оверсайзы и мужские пиджаки… | E13: ссылка | F13: 4981 | G13: 1220 | H13: 1216 | I13: 7 | J13: 87 | K13: 8 | L13: 2 | M13: =IFERROR(G13/F13,"") -> 0.24493074 | N13: =IFERROR(H13/G13,"") -> 0.99672131 | O13: =IFERROR(I13/H13,"") -> 0.0057565789 | P13: =IFERROR(J13/H13,"") -> 0.071546053 | Q13: =IFERROR(K13/H13,"") -> 0.0065789474 | R13: =IFERROR(L13/H13,"") -> 0.0016447368 | S13: =IFERROR(M13/MEDIAN(INDEX($M$5:$M$373,MATCH($A13-90,$A$5:$A$373,1)):INDEX($M$5:$M$373,MATCH($A13+90,$A$5:$A$373,1))),"") | T13: =IFERROR(N13/MEDIAN(INDEX($N$5:$N$373,MATCH($A13-90,$A$5:$A$373,1)):INDEX($N$5:$N$373,MATCH($A13+90,$A$5:$A$373,1))),"") | U13: =IFERROR(Q13/MEDIAN(INDEX($Q$5:$Q$373,MATCH($A13-90,$A$5:$A$373,1)):INDEX($Q$5:$Q$373,MATCH($A13+90,$A$5:$A$373,1))),"")
A14: 45076.417 | B14: 10 | C14: вт | D14: Я выгорела или сгорела от обиды и непонимания, даже не знаю, что было бы… | E14: ссылка | F14: 1357 | G14: 534 | H14: 529 | I14: 29 | J14: 59 | K14: 49 | L14: 4 | M14: =IFERROR(G14/F14,"") -> 0.39351511 | N14: =IFERROR(H14/G14,"") -> 0.9906367 | O14: =IFERROR(I14/H14,"") -> 0.054820416 | P14: =IFERROR(J14/H14,"") -> 0.11153119 | Q14: =IFERROR(K14/H14,"") -> 0.092627599 | R14: =IFERROR(L14/H14,"") -> 0.0075614367 | S14: =IFERROR(M14/MEDIAN(INDEX($M$5:$M$373,MATCH($A14-90,$A$5:$A$373,1)):INDEX($M$5:$M$373,MATCH($A14+90,$A$5:$A$373,1))),"") -> 1.913824 | T14: =IFERROR(N14/MEDIAN(INDEX($N$5:$N$373,MATCH($A14-90,$A$5:$A$373,1)):INDEX($N$5:$N$373,MATCH($A14+90,$A$5:$A$373,1))),"") -> 0.99326662 | U14: =IFERROR(Q14/MEDIAN(INDEX($Q$5:$Q$373,MATCH($A14-90,$A$5:$A$373,1)):INDEX($Q$5:$Q$373,MATCH($A14+90,$A$5:$A$373,1))),"") -> 17.444646
A15: 45077.375 | B15: 8 | C15: ср | D15: Если деловой образ состоит из двух цветов в одежде, это нормально? Да, это… | E15: ссылка | F15: 1022 | G15: 206 | H15: 206 | I15: 2 | J15: 20 | K15: 2 | L15: 1 | M15: =IFERROR(G15/F15,"") -> 0.20156556 | N15: =IFERROR(H15/G15,"") -> 1 | O15: =IFERROR(I15/H15,"") -> 0.0097087379 | P15: =IFERROR(J15/H15,"") -> 0.097087379 | Q15: =IFERROR(K15/H15,"") -> 0.0097087379 | R15: =IFERROR(L15/H15,"") -> 0.0048543689 | S15: =IFERROR(M15/MEDIAN(INDEX($M$5:$M$373,MATCH($A15-90,$A$5:$A$373,1)):INDEX($M$5:$M$373,MATCH($A15+90,$A$5:$A$373,1))),"") -> 0.96840595 | T15: =IFERROR(N15/MEDIAN(INDEX($N$5:$N$373,MATCH($A15-90,$A$5:$A$373,1)):INDEX($N$5:$N$373,MATCH($A15+90,$A$5:$A$373,1))),"") -> 1.0025773 | U15: =IFERROR(Q15/MEDIAN(INDEX($Q$5:$Q$373,MATCH($A15-90,$A$5:$A$373,1)):INDEX($Q$5:$Q$373,MATCH($A15+90,$A$5:$A$373,1))),"") -> 1.8220065
A16: 45078.375 | B16: 9 | C16: чт | D16: Мое отношение к российским дизайнерам Да, российские дизайнеры в одежде… | E16: ссылка | F16: 932 | G16: 217 | H16: 215 | I16: 7 | J16: 18 | K16: 0 | L16: 1 | M16: =IFERROR(G16/F16,"") -> 0.23283262 | N16: =IFERROR(H16/G16,"") -> 0.99078341 | O16: =IFERROR(I16/H16,"") -> 0.03255814 | P16: =IFERROR(J16/H16,"") -> 0.08372093 | Q16: =IFERROR(K16/H16,"") -> 0 | R16: =IFERROR(L16/H16,"") -> 0.0046511628 | S16: =IFERROR(M16/MEDIAN(INDEX($M$5:$M$373,MATCH($A16-90,$A$5:$A$373,1)):INDEX($M$5:$M$373,MATCH($A16+90,$A$5:$A$373,1))),"") -> 1.1157189 | T16: =IFERROR(N16/MEDIAN(INDEX($N$5:$N$373,MATCH($A16-90,$A$5:$A$373,1)):INDEX($N$5:$N$373,MATCH($A16+90,$A$5:$A$373,1))),"") -> 0.99341372 | U16: =IFERROR(Q16/MEDIAN(INDEX($Q$5:$Q$373,MATCH($A16-90,$A$5:$A$373,1)):INDEX($Q$5:$Q$373,MATCH($A16+90,$A$5:$A$373,1))),"") -> 0
... A373: 46215.52 | B373: 12 | C373: вс | D373: Тост Во время тоста лучше отложить вилку и телефон. Несколько минут внимания… | E373: ссылка | F373: 2704 | G373: 156 | H373: 114 | I373: 115 | J373: 29 | K373: 38 | L373: 1 | M373: =IFERROR(G373/F373,"") -> 0.057692308 | N373: =IFERROR(H373/G373,"") -> 0.73076923 | O373: =IFERROR(I373/H373,"") -> 1.0087719 | P373: =IFERROR(J373/H373,"") -> 0.25438596 | Q373: =IFERROR(K373/H373,"") -> 0.33333333 | R373: =IFERROR(L373/H373,"") -> 0.0087719298 | S373: =IFERROR(M373/MEDIAN(INDEX($M$5:$M$373,MATCH($A373-90,$A$5:$A$373,1)):INDEX($M$5:$M$373,MATCH($A373+90,$A$5:$A$373,1))),"") -> 1.0975336 | T373: =IFERROR(N373/MEDIAN(INDEX($N$5:$N$373,MATCH($A373-90,$A$5:$A$373,1)):INDEX($N$5:$N$373,MATCH($A373+90,$A$5:$A$373,1))),"") -> 0.80669331 | U373: =IFERROR(Q373/MEDIAN(INDEX($Q$5:$Q$373,MATCH($A373-90,$A$5:$A$373,1)):INDEX($Q$5:$Q$373,MATCH($A373+90,$A$5:$A$373,1))),"") -> 1.7884175

Sheet Видео
A1: Видео
A2: Длинные видео. Их всего 7 — сравнивать статистически нечего, лист справочный.
A4: Дата публикации | B4: Час | C4: День недели | D4: Заголовок | E4: Ссылка | F4: Показы | G4: Открытия | H4: Дочитывания | I4: Время просмотра, мин | J4: Лайки | K4: Комментарии | L4: Подписки | M4: CTR (открытия/показы) | N4: Дочитываемость | O4: Минут на дочитывание | P4: Лайки / дочитывания | Q4: Комментарии / дочитывания | R4: Подписки / дочитывания | S4: Индекс CTR к периоду | T4: Индекс дочитываемости к периоду | U4: Индекс комментариев к периоду
A5: 45096.5 | B5: 12 | C5: пн | D5: Студия грима Valentina Hli | E5: ссылка | F5: 753 | G5: 93 | H5: 93 | I5: 0 | J5: 7 | K5: 0 | L5: 0 | M5: =IFERROR(G5/F5,"") -> 0.12350598 | N5: =IFERROR(H5/G5,"") -> 1 | O5: =IFERROR(I5/H5,"") -> 0 | P5: =IFERROR(J5/H5,"") -> 0.075268817 | Q5: =IFERROR(K5/H5,"") -> 0 | R5: =IFERROR(L5/H5,"") -> 0 | S5: =IFERROR(M5/MEDIAN(INDEX($M$5:$M$11,MATCH($A5-90,$A$5:$A$11,1)):INDEX($M$5:$M$11,MATCH($A5+90,$A$5:$A$11,1))),"") | T5: =IFERROR(N5/MEDIAN(INDEX($N$5:$N$11,MATCH($A5-90,$A$5:$A$11,1)):INDEX($N$5:$N$11,MATCH($A5+90,$A$5:$A$11,1))),"") | U5: =IFERROR(Q5/MEDIAN(INDEX($Q$5:$Q$11,MATCH($A5-90,$A$5:$A$11,1)):INDEX($Q$5:$Q$11,MATCH($A5+90,$A$5:$A$11,1))),"")
A6: 45096.85 | B6: 20 | C6: пн | D6: Студия грима Valentina Hli | E6: ссылка | F6: 72141 | G6: 1607 | H6: 2093 | I6: 0 | J6: 131 | K6: 7 | L6: 8 | M6: =IFERROR(G6/F6,"") -> 0.022275821 | N6: =IFERROR(H6/G6,"") -> 1.3024269 | O6: =IFERROR(I6/H6,"") -> 0 | P6: =IFERROR(J6/H6,"") -> 0.062589584 | Q6: =IFERROR(K6/H6,"") -> 0.0033444816 | R6: =IFERROR(L6/H6,"") -> 0.0038222647 | S6: =IFERROR(M6/MEDIAN(INDEX($M$5:$M$11,MATCH($A6-90,$A$5:$A$11,1)):INDEX($M$5:$M$11,MATCH($A6+90,$A$5:$A$11,1))),"") | T6: =IFERROR(N6/MEDIAN(INDEX($N$5:$N$11,MATCH($A6-90,$A$5:$A$11,1)):INDEX($N$5:$N$11,MATCH($A6+90,$A$5:$A$11,1))),"") | U6: =IFERROR(Q6/MEDIAN(INDEX($Q$5:$Q$11,MATCH($A6-90,$A$5:$A$11,1)):INDEX($Q$5:$Q$11,MATCH($A6+90,$A$5:$A$11,1))),"")
A7: 45140.5 | B7: 12 | C7: ср | D7: Уникальный мастер-класс по гриму и спецэффектам в кино | E7: ссылка | F7: 284527 | G7: 3652 | H7: 4240 | I7: 662 | J7: 131 | K7: 10 | L7: 26 | M7: =IFERROR(G7/F7,"") -> 0.012835337 | N7: =IFERROR(H7/G7,"") -> 1.1610077 | O7: =IFERROR(I7/H7,"") -> 0.15613208 | P7: =IFERROR(J7/H7,"") -> 0.030896226 | Q7: =IFERROR(K7/H7,"") -> 0.0023584906 | R7: =IFERROR(L7/H7,"") -> 0.0061320755 | S7: =IFERROR(M7/MEDIAN(INDEX($M$5:$M$11,MATCH($A7-90,$A$5:$A$11,1)):INDEX($M$5:$M$11,MATCH($A7+90,$A$5:$A$11,1))),"") | T7: =IFERROR(N7/MEDIAN(INDEX($N$5:$N$11,MATCH($A7-90,$A$5:$A$11,1)):INDEX($N$5:$N$11,MATCH($A7+90,$A$5:$A$11,1))),"") | U7: =IFERROR(Q7/MEDIAN(INDEX($Q$5:$Q$11,MATCH($A7-90,$A$5:$A$11,1)):INDEX($Q$5:$Q$11,MATCH($A7+90,$A$5:$A$11,1))),"")
A8: 45202.85 | B8: 20 | C8: вт | D8: Китайский этикет: подарки, застолье, стереотипы | E8: ссылка | F8: 998495 | G8: 7070 | H8: 8808 | I8: 3309 | J8: 219 | K8: 9 | L8: 61 | M8: =IFERROR(G8/F8,"") -> 0.0070806564 | N8: =IFERROR(H8/G8,"") -> 1.2458274 | O8: =IFERROR(I8/H8,"") -> 0.3756812 | P8: =IFERROR(J8/H8,"") -> 0.02486376 | Q8: =IFERROR(K8/H8,"") -> 0.0010217984 | R8: =IFERROR(L8/H8,"") -> 0.0069255223 | S8: =IFERROR(M8/MEDIAN(INDEX($M$5:$M$11,MATCH($A8-90,$A$5:$A$11,1)):INDEX($M$5:$M$11,MATCH($A8+90,$A$5:$A$11,1))),"") -> 0.48935081 | T8: =IFERROR(N8/MEDIAN(INDEX($N$5:$N$11,MATCH($A8-90,$A$5:$A$11,1)):INDEX($N$5:$N$11,MATCH($A8+90,$A$5:$A$11,1))),"") -> 0.97778893 | U8: =IFERROR(Q8/MEDIAN(INDEX($Q$5:$Q$11,MATCH($A8-90,$A$5:$A$11,1)):INDEX($Q$5:$Q$11,MATCH($A8+90,$A$5:$A$11,1))),"") -> 0.57300599
A9: 45216.948 | B9: 22 | C9: вт | D9: Этикет в начальной школе. Практика и теория. Интервью с учителем из школы Нижнего Новгорода | E9: ссылка | F9: 1899044 | G9: 15281 | H9: 34975 | I9: 1104 | J9: 202 | K9: 25 | L9: 122 | M9: =IFERROR(G9/F9,"") -> 0.0080466803 | N9: =IFERROR(H9/G9,"") -> 2.28879 | O9: =IFERROR(I9/H9,"") -> 0.031565404 | P9: =IFERROR(J9/H9,"") -> 0.005775554 | Q9: =IFERROR(K9/H9,"") -> 0.00071479628 | R9: =IFERROR(L9/H9,"") -> 0.0034882059 | S9: =IFERROR(M9/MEDIAN(INDEX($M$5:$M$11,MATCH($A9-90,$A$5:$A$11,1)):INDEX($M$5:$M$11,MATCH($A9+90,$A$5:$A$11,1))),"") -> 0.55611364 | T9: =IFERROR(N9/MEDIAN(INDEX($N$5:$N$11,MATCH($A9-90,$A$5:$A$11,1)):INDEX($N$5:$N$11,MATCH($A9+90,$A$5:$A$11,1))),"") -> 1.7963592 | U9: =IFERROR(Q9/MEDIAN(INDEX($Q$5:$Q$11,MATCH($A9-90,$A$5:$A$11,1)):INDEX($Q$5:$Q$11,MATCH($A9+90,$A$5:$A$11,1))),"") -> 0.40084479
A10: 45235.625 | B10: 15 | C10: вс | D10: Церковный этикет. Исаакиевский собор. | E10: ссылка | F10: 1239968 | G10: 19968 | H10: 23680 | I10: 7021 | J10: 512 | K10: 45 | L10: 180 | M10: =IFERROR(G10/F10,"") -> 0.016103641 | N10: =IFERROR(H10/G10,"") -> 1.1858974 | O10: =IFERROR(I10/H10,"") -> 0.29649493 | P10: =IFERROR(J10/H10,"") -> 0.021621622 | Q10: =IFERROR(K10/H10,"") -> 0.0019003378 | R10: =IFERROR(L10/H10,"") -> 0.0076013514 | S10: =IFERROR(M10/MEDIAN(INDEX($M$5:$M$11,MATCH($A10-90,$A$5:$A$11,1)):INDEX($M$5:$M$11,MATCH($A10+90,$A$5:$A$11,1))),"") -> 1.2546333 | T10: =IFERROR(N10/MEDIAN(INDEX($N$5:$N$11,MATCH($A10-90,$A$5:$A$11,1)):INDEX($N$5:$N$11,MATCH($A10+90,$A$5:$A$11,1))),"") -> 0.95189542 | U10: =IFERROR(Q10/MEDIAN(INDEX($Q$5:$Q$11,MATCH($A10-90,$A$5:$A$11,1)):INDEX($Q$5:$Q$11,MATCH($A10+90,$A$5:$A$11,1))),"") -> 1.1405828
A11: 45269.702 | B11: 16 | C11: сб | D11: 82-я годовщина парада 7 ноября 1941 года: за кулисами со студией грима Valentina Hli | E11: ссылка | F11: 91387 | G11: 2255 | H11: 3001 | I11: 299 | J11: 154 | K11: 5 | L11: 30 | M11: =IFERROR(G11/F11,"") -> 0.024675282 | N11: =IFERROR(H11/G11,"") -> 1.3308204 | O11: =IFERROR(I11/H11,"") -> 0.099633456 | P11: =IFERROR(J11/H11,"") -> 0.051316228 | Q11: =IFERROR(K11/H11,"") -> 0.0016661113 | R11: =IFERROR(L11/H11,"") -> 0.0099966678 | S11: =IFERROR(M11/MEDIAN(INDEX($M$5:$M$11,MATCH($A11-90,$A$5:$A$11,1)):INDEX($M$5:$M$11,MATCH($A11+90,$A$5:$A$11,1))),"") -> 1.9224491 | T11: =IFERROR(N11/MEDIAN(INDEX($N$5:$N$11,MATCH($A11-90,$A$5:$A$11,1)):INDEX($N$5:$N$11,MATCH($A11+90,$A$5:$A$11,1))),"") -> 1.0682221 | U11: =IFERROR(Q11/MEDIAN(INDEX($Q$5:$Q$11,MATCH($A11-90,$A$5:$A$11,1)):INDEX($Q$5:$Q$11,MATCH($A11+90,$A$5:$A$11,1))),"") -> 1
